{"Twin Falls ID": {"min_value": 2, "values": {"chicago_blackhawks": {"team_key": "/sport/hockey/team:22", "value": 2}, "boston_bruins": {"team_key": "/sport/hockey/team:3", "value": 4}, "san_jose_sharks": {"team_key": "/sport/hockey/team:21", "value": 9}, "new_york_rangers": {"team_key": "/sport/hockey/team:6", "value": 3}, "los_angeles_kings": {"team_key": "/sport/hockey/team:23", "value": 7}}}, "Orlando-Daytona Beach-Melbourne FL": {"min_value": 9, "values": {"new_york_rangers": {"team_key": "/sport/hockey/team:6", "value": 9}, "toronto_maple_leafs": {"team_key": "/sport/hockey/team:8", "value": 23}, "florida_panthers": {"team_key": "/sport/hockey/team:14", "value": 24}, "tampa_bay_lightning": {"team_key": "/sport/hockey/team:17", "value": 20}, "edmonton_oilers": {"team_key": "/sport/hockey/team:24", "value": 11}}}, "Yuma AZ-El Centro CA": {"min_value": 21, "values": {"calgary_flames": {"team_key": "/sport/hockey/team:18", "value": 21}, "vancouver_canucks": {"team_key": "/sport/hockey/team:26", "value": 27}, "toronto_maple_leafs": {"team_key": "/sport/hockey/team:8", "value": 26}, "edmonton_oilers": {"team_key": "/sport/hockey/team:24", "value": 56}, "anaheim_ducks": {"team_key": "/sport/hockey/team:25", "value": 22}}}, "Milwaukee WI": {"min_value": 7, "values": {"chicago_blackhawks": {"team_key": "/sport/hockey/team:22", "value": 16}, "calgary_flames": {"team_key": "/sport/hockey/team:18", "value": 8}, "toronto_maple_leafs": {"team_key": "/sport/hockey/team:8", "value": 22}, "edmonton_oilers": {"team_key": "/sport/hockey/team:24", "value": 11}, "winnipeg_jets": {"team_key": "/sport/hockey/team:28", "value": 7}}}, "Santa Barbara-Santa Maria-San Luis Obispo CA": {"min_value": 13, "values": {"los_angeles_kings": {"team_key": "/sport/hockey/team:23", "value": 50}, "san_jose_sharks": {"team_key": "/sport/hockey/team:21", "value": 22}, "toronto_maple_leafs": {"team_key": "/sport/hockey/team:8", "value": 17}, "edmonton_oilers": {"team_key": "/sport/hockey/team:24", "value": 13}, "anaheim_ducks": {"team_key": "/sport/hockey/team:25", "value": 32}}}, "Victoria TX": {"min_value": 2, "values": {"chicago_blackhawks": {"team_key": "/sport/hockey/team:22", "value": 2}}}, "Butte-Bozeman Mount": {"min_value": 9, "values": {"los_angeles_kings": {"team_key": "/sport/hockey/team:23", "value": 9}, "vancouver_canucks": {"team_key": "/sport/hockey/team:26", "value": 14}, "anaheim_ducks": {"team_key": "/sport/hockey/team:25", "value": 18}, "calgary_flames": {"team_key": "/sport/hockey/team:18", "value": 46}, "colorado_avalanche": {"team_key": "/sport/hockey/team:1", "value": 16}}}, "Palm Springs CA": {"min_value": 52, "values": {"vancouver_canucks": {"team_key": "/sport/hockey/team:26", "value": 100}, "winnipeg_jets": {"team_key": "/sport/hockey/team:28", "value": 52}, "calgary_flames": {"team_key": "/sport/hockey/team:18", "value": 100}, "edmonton_oilers": {"team_key": "/sport/hockey/team:24", "value": 100}, "anaheim_ducks": {"team_key": "/sport/hockey/team:25", "value": 59}}}, "Seattle-Tacoma WA": {"min_value": 9, "values": {"calgary_flames": {"team_key": "/sport/hockey/team:18", "value": 9}, "vancouver_canucks": {"team_key": "/sport/hockey/team:26", "value": 33}, "toronto_maple_leafs": {"team_key": "/sport/hockey/team:8", "value": 18}, "edmonton_oilers": {"team_key": "/sport/hockey/team:24", "value": 18}, "anaheim_ducks": {"team_key": "/sport/hockey/team:25", "value": 11}}}, "San Antonio TX": {"min_value": 3, "values": {"new_jersey_devils": {"team_key": "/sport/hockey/team:13", "value": 3}, "dallas_stars": {"team_key": "/sport/hockey/team:20", "value": 8}, "toronto_maple_leafs": {"team_key": "/sport/hockey/team:8", "value": 11}, "edmonton_oilers": {"team_key": "/sport/hockey/team:24", "value": 12}, "anaheim_ducks": {"team_key": "/sport/hockey/team:25", "value": 3}}}, "Colorado Springs-Pueblo CO": {"min_value": 9, "values": {"calgary_flames": {"team_key": "/sport/hockey/team:18", "value": 9}, "colorado_avalanche": {"team_key": "/sport/hockey/team:1", "value": 71}, "toronto_maple_leafs": {"team_key": "/sport/hockey/team:8", "value": 17}, "edmonton_oilers": {"team_key": "/sport/hockey/team:24", "value": 13}, "winnipeg_jets": {"team_key": "/sport/hockey/team:28", "value": 10}}}, "Alexandria LA": {"min_value": 1, "values": {"chicago_blackhawks": {"team_key": "/sport/hockey/team:22", "value": 2}, "boston_bruins": {"team_key": "/sport/hockey/team:3", "value": 1}, "montreal_canadiens": {"team_key": "/sport/hockey/team:11", "value": 3}, "los_angeles_kings": {"team_key": "/sport/hockey/team:23", "value": 3}, "minnesota_wild": {"team_key": "/sport/hockey/team:29", "value": 1}}}, "La Crosse-Eau Claire WI": {"min_value": 11, "values": {"calgary_flames": {"team_key": "/sport/hockey/team:18", "value": 11}, "toronto_maple_leafs": {"team_key": "/sport/hockey/team:8", "value": 20}, "minnesota_wild": {"team_key": "/sport/hockey/team:29", "value": 28}, "edmonton_oilers": {"team_key": "/sport/hockey/team:24", "value": 14}, "winnipeg_jets": {"team_key": "/sport/hockey/team:28", "value": 14}}}, "Wheeling WV-Steubenville OH": {"min_value": 11, "values": {"columbus_blue_jackets": {"team_key": "/sport/hockey/team:30", "value": 12}, "new_york_islanders": {"team_key": "/sport/hockey/team:4", "value": 11}, "montreal_canadiens": {"team_key": "/sport/hockey/team:11", "value": 12}, "toronto_maple_leafs": {"team_key": "/sport/hockey/team:8", "value": 28}, "pittsburgh_penguins": {"team_key": "/sport/hockey/team:7", "value": 44}}}, "Buffalo NY": {"min_value": 30, "values": {"buffalo_sabres": {"team_key": "/sport/hockey/team:10", "value": 100}, "calgary_flames": {"team_key": "/sport/hockey/team:18", "value": 30}, "toronto_maple_leafs": {"team_key": "/sport/hockey/team:8", "value": 99}, "edmonton_oilers": {"team_key": "/sport/hockey/team:24", "value": 65}, "winnipeg_jets": {"team_key": "/sport/hockey/team:28", "value": 33}}}, "Des Moines-Ames IA": {"min_value": 6, "values": {"chicago_blackhawks": {"team_key": "/sport/hockey/team:22", "value": 8}, "toronto_maple_leafs": {"team_key": "/sport/hockey/team:8", "value": 20}, "minnesota_wild": {"team_key": "/sport/hockey/team:29", "value": 6}, "edmonton_oilers": {"team_key": "/sport/hockey/team:24", "value": 14}, "anaheim_ducks": {"team_key": "/sport/hockey/team:25", "value": 6}}}, "Laredo TX": {"min_value": 1, "values": {"boston_bruins": {"team_key": "/sport/hockey/team:3", "value": 1}, "dallas_stars": {"team_key": "/sport/hockey/team:20", "value": 11}, "los_angeles_kings": {"team_key": "/sport/hockey/team:23", "value": 4}, "detroit_red_wings": {"team_key": "/sport/hockey/team:2", "value": 1}, "montreal_canadiens": {"team_key": "/sport/hockey/team:11", "value": 3}}}, "Knoxville TN": {"min_value": 4, "values": {"nashville_predators": {"team_key": "/sport/hockey/team:27", "value": 18}, "winnipeg_jets": {"team_key": "/sport/hockey/team:28", "value": 5}, "toronto_maple_leafs": {"team_key": "/sport/hockey/team:8", "value": 14}, "edmonton_oilers": {"team_key": "/sport/hockey/team:24", "value": 10}, "anaheim_ducks": {"team_key": "/sport/hockey/team:25", "value": 4}}}, "Las Vegas NV": {"min_value": 14, "values": {"los_angeles_kings": {"team_key": "/sport/hockey/team:23", "value": 23}, "calgary_flames": {"team_key": "/sport/hockey/team:18", "value": 14}, "toronto_maple_leafs": {"team_key": "/sport/hockey/team:8", "value": 24}, "edmonton_oilers": {"team_key": "/sport/hockey/team:24", "value": 20}, "anaheim_ducks": {"team_key": "/sport/hockey/team:25", "value": 23}}}, "Tampa-St. Petersburg (Sarasota) FL": {"min_value": 12, "values": {"new_york_islanders": {"team_key": "/sport/hockey/team:4", "value": 12}, "montreal_canadiens": {"team_key": "/sport/hockey/team:11", "value": 14}, "toronto_maple_leafs": {"team_key": "/sport/hockey/team:8", "value": 37}, "florida_panthers": {"team_key": "/sport/hockey/team:14", "value": 18}, "tampa_bay_lightning": {"team_key": "/sport/hockey/team:17", "value": 100}}}, "Portland-Auburn ME": {"min_value": 12, "values": {"boston_bruins": {"team_key": "/sport/hockey/team:3", "value": 56}, "montreal_canadiens": {"team_key": "/sport/hockey/team:11", "value": 39}, "toronto_maple_leafs": {"team_key": "/sport/hockey/team:8", "value": 35}, "edmonton_oilers": {"team_key": "/sport/hockey/team:24", "value": 15}, "winnipeg_jets": {"team_key": "/sport/hockey/team:28", "value": 12}}}, "San Diego CA": {"min_value": 9, "values": {"los_angeles_kings": {"team_key": "/sport/hockey/team:23", "value": 40}, "vancouver_canucks": {"team_key": "/sport/hockey/team:26", "value": 9}, "toronto_maple_leafs": {"team_key": "/sport/hockey/team:8", "value": 18}, "edmonton_oilers": {"team_key": "/sport/hockey/team:24", "value": 14}, "anaheim_ducks": {"team_key": "/sport/hockey/team:25", "value": 62}}}, "Panama City FL": {"min_value": 5, "values": {"vancouver_canucks": {"team_key": "/sport/hockey/team:26", "value": 5}, "new_york_islanders": {"team_key": "/sport/hockey/team:4", "value": 6}, "toronto_maple_leafs": {"team_key": "/sport/hockey/team:8", "value": 35}, "florida_panthers": {"team_key": "/sport/hockey/team:14", "value": 9}, "tampa_bay_lightning": {"team_key": "/sport/hockey/team:17", "value": 6}}}, "Albany GA": {"min_value": 1, "values": {"chicago_blackhawks": {"team_key": "/sport/hockey/team:22", "value": 1}, "tampa_bay_lightning": {"team_key": "/sport/hockey/team:17", "value": 2}, "detroit_red_wings": {"team_key": "/sport/hockey/team:2", "value": 1}, "philadelphia_flyers": {"team_key": "/sport/hockey/team:12", "value": 2}, "los_angeles_kings": {"team_key": "/sport/hockey/team:23", "value": 1}}}, "Quincy IL-Hannibal MO-Keokuk IA": {"min_value": 6, "values": {"chicago_blackhawks": {"team_key": "/sport/hockey/team:22", "value": 21}, "vancouver_canucks": {"team_key": "/sport/hockey/team:26", "value": 8}, "anaheim_ducks": {"team_key": "/sport/hockey/team:25", "value": 7}, "dallas_stars": {"team_key": "/sport/hockey/team:20", "value": 6}, "st._louis_blues": {"team_key": "/sport/hockey/team:16", "value": 30}}}, "Fresno-Visalia CA": {"min_value": 16, "values": {"new_york_islanders": {"team_key": "/sport/hockey/team:4", "value": 26}, "new_york_rangers": {"team_key": "/sport/hockey/team:6", "value": 23}, "toronto_maple_leafs": {"team_key": "/sport/hockey/team:8", "value": 21}, "san_jose_sharks": {"team_key": "/sport/hockey/team:21", "value": 18}, "edmonton_oilers": {"team_key": "/sport/hockey/team:24", "value": 16}}}, "Chicago IL": {"min_value": 13, "values": {"chicago_blackhawks": {"team_key": "/sport/hockey/team:22", "value": 100}, "winnipeg_jets": {"team_key": "/sport/hockey/team:28", "value": 13}, "toronto_maple_leafs": {"team_key": "/sport/hockey/team:8", "value": 31}, "edmonton_oilers": {"team_key": "/sport/hockey/team:24", "value": 20}, "anaheim_ducks": {"team_key": "/sport/hockey/team:25", "value": 14}}}, "Elmira NY": {"min_value": 14, "values": {"new_jersey_devils": {"team_key": "/sport/hockey/team:13", "value": 14}, "new_york_islanders": {"team_key": "/sport/hockey/team:4", "value": 18}, "new_york_rangers": {"team_key": "/sport/hockey/team:6", "value": 29}, "toronto_maple_leafs": {"team_key": "/sport/hockey/team:8", "value": 37}, "montreal_canadiens": {"team_key": "/sport/hockey/team:11", "value": 18}}}, "Rapid City SD": {"min_value": 5, "values": {"colorado_avalanche": {"team_key": "/sport/hockey/team:1", "value": 14}, "montreal_canadiens": {"team_key": "/sport/hockey/team:11", "value": 11}, "los_angeles_kings": {"team_key": "/sport/hockey/team:23", "value": 9}, "minnesota_wild": {"team_key": "/sport/hockey/team:29", "value": 5}, "anaheim_ducks": {"team_key": "/sport/hockey/team:25", "value": 6}}}, "Greenville-Spartanburg SC-Asheville NC-Anderson SC": {"min_value": 4, "values": {"vancouver_canucks": {"team_key": "/sport/hockey/team:26", "value": 4}, "winnipeg_jets": {"team_key": "/sport/hockey/team:28", "value": 5}, "toronto_maple_leafs": {"team_key": "/sport/hockey/team:8", "value": 17}, "edmonton_oilers": {"team_key": "/sport/hockey/team:24", "value": 8}, "carolina_hurricanes": {"team_key": "/sport/hockey/team:5", "value": 8}}}, "Kansas City MO": {"min_value": 5, "values": {"new_jersey_devils": {"team_key": "/sport/hockey/team:13", "value": 5}, "st._louis_blues": {"team_key": "/sport/hockey/team:16", "value": 9}, "toronto_maple_leafs": {"team_key": "/sport/hockey/team:8", "value": 16}, "edmonton_oilers": {"team_key": "/sport/hockey/team:24", "value": 11}, "winnipeg_jets": {"team_key": "/sport/hockey/team:28", "value": 6}}}, "Presque Isle ME": {"min_value": 10, "values": {"boston_bruins": {"team_key": "/sport/hockey/team:3", "value": 62}, "vancouver_canucks": {"team_key": "/sport/hockey/team:26", "value": 15}, "new_york_rangers": {"team_key": "/sport/hockey/team:6", "value": 10}, "toronto_maple_leafs": {"team_key": "/sport/hockey/team:8", "value": 63}, "montreal_canadiens": {"team_key": "/sport/hockey/team:11", "value": 65}}}, "Casper-Riverton WY": {"min_value": 4, "values": {"chicago_blackhawks": {"team_key": "/sport/hockey/team:22", "value": 4}, "colorado_avalanche": {"team_key": "/sport/hockey/team:1", "value": 45}, "san_jose_sharks": {"team_key": "/sport/hockey/team:21", "value": 8}, "arizona_coyotes": {"team_key": "/sport/hockey/team:19", "value": 12}, "los_angeles_kings": {"team_key": "/sport/hockey/team:23", "value": 4}}}, "Grand Junction-Montrose CO": {"min_value": 4, "values": {"colorado_avalanche": {"team_key": "/sport/hockey/team:1", "value": 67}, "san_jose_sharks": {"team_key": "/sport/hockey/team:21", "value": 4}, "anaheim_ducks": {"team_key": "/sport/hockey/team:25", "value": 5}, "los_angeles_kings": {"team_key": "/sport/hockey/team:23", "value": 8}, "vancouver_canucks": {"team_key": "/sport/hockey/team:26", "value": 5}}}, "Los Angeles CA": {"min_value": 9, "values": {"los_angeles_kings": {"team_key": "/sport/hockey/team:23", "value": 100}, "vancouver_canucks": {"team_key": "/sport/hockey/team:26", "value": 9}, "toronto_maple_leafs": {"team_key": "/sport/hockey/team:8", "value": 19}, "edmonton_oilers": {"team_key": "/sport/hockey/team:24", "value": 14}, "anaheim_ducks": {"team_key": "/sport/hockey/team:25", "value": 100}}}, "Columbia-Jefferson City MO": {"min_value": 8, "values": {"chicago_blackhawks": {"team_key": "/sport/hockey/team:22", "value": 8}, "st._louis_blues": {"team_key": "/sport/hockey/team:16", "value": 36}, "montreal_canadiens": {"team_key": "/sport/hockey/team:11", "value": 8}, "toronto_maple_leafs": {"team_key": "/sport/hockey/team:8", "value": 15}, "edmonton_oilers": {"team_key": "/sport/hockey/team:24", "value": 11}}}, "Cedar Rapids-Waterloo-Iowa City & Dubuque IA": {"min_value": 8, "values": {"chicago_blackhawks": {"team_key": "/sport/hockey/team:22", "value": 15}, "calgary_flames": {"team_key": "/sport/hockey/team:18", "value": 9}, "toronto_maple_leafs": {"team_key": "/sport/hockey/team:8", "value": 20}, "edmonton_oilers": {"team_key": "/sport/hockey/team:24", "value": 12}, "anaheim_ducks": {"team_key": "/sport/hockey/team:25", "value": 8}}}, "Missoula Mount": {"min_value": 10, "values": {"calgary_flames": {"team_key": "/sport/hockey/team:18", "value": 64}, "vancouver_canucks": {"team_key": "/sport/hockey/team:26", "value": 10}, "toronto_maple_leafs": {"team_key": "/sport/hockey/team:8", "value": 25}, "edmonton_oilers": {"team_key": "/sport/hockey/team:24", "value": 32}, "anaheim_ducks": {"team_key": "/sport/hockey/team:25", "value": 13}}}, "Zanesville OH": {"min_value": 2, "values": {"boston_bruins": {"team_key": "/sport/hockey/team:3", "value": 2}, "detroit_red_wings": {"team_key": "/sport/hockey/team:2", "value": 3}, "columbus_blue_jackets": {"team_key": "/sport/hockey/team:30", "value": 61}, "pittsburgh_penguins": {"team_key": "/sport/hockey/team:7", "value": 5}, "anaheim_ducks": {"team_key": "/sport/hockey/team:25", "value": 9}}}, "Rochester MN-Mason City IA-Austin MN": {"min_value": 10, "values": {"winnipeg_jets": {"team_key": "/sport/hockey/team:28", "value": 16}, "toronto_maple_leafs": {"team_key": "/sport/hockey/team:8", "value": 27}, "minnesota_wild": {"team_key": "/sport/hockey/team:29", "value": 62}, "edmonton_oilers": {"team_key": "/sport/hockey/team:24", "value": 21}, "anaheim_ducks": {"team_key": "/sport/hockey/team:25", "value": 10}}}, "Chattanooga TN": {"min_value": 3, "values": {"new_jersey_devils": {"team_key": "/sport/hockey/team:13", "value": 3}, "vancouver_canucks": {"team_key": "/sport/hockey/team:26", "value": 3}, "montreal_canadiens": {"team_key": "/sport/hockey/team:11", "value": 4}, "toronto_maple_leafs": {"team_key": "/sport/hockey/team:8", "value": 15}, "nashville_predators": {"team_key": "/sport/hockey/team:27", "value": 16}}}, "Grand Rapids-Kalamazoo-Battle Creek MI": {"min_value": 10, "values": {"montreal_canadiens": {"team_key": "/sport/hockey/team:11", "value": 10}, "toronto_maple_leafs": {"team_key": "/sport/hockey/team:8", "value": 30}, "detroit_red_wings": {"team_key": "/sport/hockey/team:2", "value": 48}, "edmonton_oilers": {"team_key": "/sport/hockey/team:24", "value": 18}, "winnipeg_jets": {"team_key": "/sport/hockey/team:28", "value": 12}}}, "Springfield-Holyoke MA": {"min_value": 19, "values": {"boston_bruins": {"team_key": "/sport/hockey/team:3", "value": 57}, "new_york_islanders": {"team_key": "/sport/hockey/team:4", "value": 19}, "montreal_canadiens": {"team_key": "/sport/hockey/team:11", "value": 27}, "toronto_maple_leafs": {"team_key": "/sport/hockey/team:8", "value": 38}, "edmonton_oilers": {"team_key": "/sport/hockey/team:24", "value": 28}}}, "Houston TX": {"min_value": 4, "values": {"calgary_flames": {"team_key": "/sport/hockey/team:18", "value": 9}, "dallas_stars": {"team_key": "/sport/hockey/team:20", "value": 9}, "toronto_maple_leafs": {"team_key": "/sport/hockey/team:8", "value": 15}, "edmonton_oilers": {"team_key": "/sport/hockey/team:24", "value": 40}, "anaheim_ducks": {"team_key": "/sport/hockey/team:25", "value": 4}}}, "Parkersburg WV": {"min_value": 2, "values": {"detroit_red_wings": {"team_key": "/sport/hockey/team:2", "value": 2}, "anaheim_ducks": {"team_key": "/sport/hockey/team:25", "value": 9}, "columbus_blue_jackets": {"team_key": "/sport/hockey/team:30", "value": 10}, "washington_capitals": {"team_key": "/sport/hockey/team:15", "value": 5}, "pittsburgh_penguins": {"team_key": "/sport/hockey/team:7", "value": 8}}}, "Lincoln & Hastings-Kearney NE": {"min_value": 5, "values": {"colorado_avalanche": {"team_key": "/sport/hockey/team:1", "value": 6}, "new_york_islanders": {"team_key": "/sport/hockey/team:4", "value": 7}, "toronto_maple_leafs": {"team_key": "/sport/hockey/team:8", "value": 10}, "edmonton_oilers": {"team_key": "/sport/hockey/team:24", "value": 8}, "anaheim_ducks": {"team_key": "/sport/hockey/team:25", "value": 5}}}, "Ft. Myers-Naples FL": {"min_value": 16, "values": {"montreal_canadiens": {"team_key": "/sport/hockey/team:11", "value": 18}, "toronto_maple_leafs": {"team_key": "/sport/hockey/team:8", "value": 65}, "florida_panthers": {"team_key": "/sport/hockey/team:14", "value": 45}, "tampa_bay_lightning": {"team_key": "/sport/hockey/team:17", "value": 17}, "edmonton_oilers": {"team_key": "/sport/hockey/team:24", "value": 16}}}, "Ft. Wayne IN": {"min_value": 6, "values": {"new_jersey_devils": {"team_key": "/sport/hockey/team:13", "value": 6}, "chicago_blackhawks": {"team_key": "/sport/hockey/team:22", "value": 10}, "montreal_canadiens": {"team_key": "/sport/hockey/team:11", "value": 9}, "toronto_maple_leafs": {"team_key": "/sport/hockey/team:8", "value": 26}, "anaheim_ducks": {"team_key": "/sport/hockey/team:25", "value": 7}}}, "Tri-Cities TN-VA": {"min_value": 2, "values": {"nashville_predators": {"team_key": "/sport/hockey/team:27", "value": 9}, "winnipeg_jets": {"team_key": "/sport/hockey/team:28", "value": 3}, "toronto_maple_leafs": {"team_key": "/sport/hockey/team:8", "value": 20}, "washington_capitals": {"team_key": "/sport/hockey/team:15", "value": 3}, "anaheim_ducks": {"team_key": "/sport/hockey/team:25", "value": 2}}}, "Tulsa OK": {"min_value": 5, "values": {"new_york_islanders": {"team_key": "/sport/hockey/team:4", "value": 5}, "dallas_stars": {"team_key": "/sport/hockey/team:20", "value": 5}, "toronto_maple_leafs": {"team_key": "/sport/hockey/team:8", "value": 13}, "edmonton_oilers": {"team_key": "/sport/hockey/team:24", "value": 39}, "montreal_canadiens": {"team_key": "/sport/hockey/team:11", "value": 5}}}, "Omaha NE": {"min_value": 7, "values": {"winnipeg_jets": {"team_key": "/sport/hockey/team:28", "value": 8}, "toronto_maple_leafs": {"team_key": "/sport/hockey/team:8", "value": 17}, "minnesota_wild": {"team_key": "/sport/hockey/team:29", "value": 8}, "edmonton_oilers": {"team_key": "/sport/hockey/team:24", "value": 14}, "anaheim_ducks": {"team_key": "/sport/hockey/team:25", "value": 7}}}, "Savannah GA": {"min_value": 6, "values": {"new_jersey_devils": {"team_key": "/sport/hockey/team:13", "value": 6}, "montreal_canadiens": {"team_key": "/sport/hockey/team:11", "value": 7}, "toronto_maple_leafs": {"team_key": "/sport/hockey/team:8", "value": 21}, "edmonton_oilers": {"team_key": "/sport/hockey/team:24", "value": 7}, "winnipeg_jets": {"team_key": "/sport/hockey/team:28", "value": 6}}}, "Greenwood-Greenville MS": {"min_value": 1, "values": {"boston_bruins": {"team_key": "/sport/hockey/team:3", "value": 1}}}, "Lubbock TX": {"min_value": 3, "values": {"calgary_flames": {"team_key": "/sport/hockey/team:18", "value": 8}, "vancouver_canucks": {"team_key": "/sport/hockey/team:26", "value": 3}, "dallas_stars": {"team_key": "/sport/hockey/team:20", "value": 30}, "toronto_maple_leafs": {"team_key": "/sport/hockey/team:8", "value": 15}, "montreal_canadiens": {"team_key": "/sport/hockey/team:11", "value": 6}}}, "Clarksburg-Weston WV": {"min_value": 3, "values": {"pittsburgh_penguins": {"team_key": "/sport/hockey/team:7", "value": 14}, "new_york_rangers": {"team_key": "/sport/hockey/team:6", "value": 4}, "washington_capitals": {"team_key": "/sport/hockey/team:15", "value": 12}, "tampa_bay_lightning": {"team_key": "/sport/hockey/team:17", "value": 3}, "ottawa_senators": {"team_key": "/sport/hockey/team:9", "value": 5}}}, "Spokane WA": {"min_value": 9, "values": {"calgary_flames": {"team_key": "/sport/hockey/team:18", "value": 13}, "vancouver_canucks": {"team_key": "/sport/hockey/team:26", "value": 16}, "toronto_maple_leafs": {"team_key": "/sport/hockey/team:8", "value": 21}, "edmonton_oilers": {"team_key": "/sport/hockey/team:24", "value": 21}, "anaheim_ducks": {"team_key": "/sport/hockey/team:25", "value": 9}}}, "Amarillo TX": {"min_value": 4, "values": {"new_jersey_devils": {"team_key": "/sport/hockey/team:13", "value": 6}, "calgary_flames": {"team_key": "/sport/hockey/team:18", "value": 4}, "dallas_stars": {"team_key": "/sport/hockey/team:20", "value": 18}, "toronto_maple_leafs": {"team_key": "/sport/hockey/team:8", "value": 17}, "edmonton_oilers": {"team_key": "/sport/hockey/team:24", "value": 14}}}, "Bowling Green KY": {"min_value": 12, "values": {"nashville_predators": {"team_key": "/sport/hockey/team:27", "value": 20}, "new_york_islanders": {"team_key": "/sport/hockey/team:4", "value": 15}, "new_york_rangers": {"team_key": "/sport/hockey/team:6", "value": 12}, "toronto_maple_leafs": {"team_key": "/sport/hockey/team:8", "value": 17}, "edmonton_oilers": {"team_key": "/sport/hockey/team:24", "value": 19}}}, "Wichita Falls TX & Lawton OK": {"min_value": 2, "values": {"vancouver_canucks": {"team_key": "/sport/hockey/team:26", "value": 4}, "dallas_stars": {"team_key": "/sport/hockey/team:20", "value": 25}, "los_angeles_kings": {"team_key": "/sport/hockey/team:23", "value": 4}, "detroit_red_wings": {"team_key": "/sport/hockey/team:2", "value": 2}, "anaheim_ducks": {"team_key": "/sport/hockey/team:25", "value": 5}}}, "Bend OR": {"min_value": 5, "values": {"vancouver_canucks": {"team_key": "/sport/hockey/team:26", "value": 10}, "san_jose_sharks": {"team_key": "/sport/hockey/team:21", "value": 5}, "montreal_canadiens": {"team_key": "/sport/hockey/team:11", "value": 5}, "los_angeles_kings": {"team_key": "/sport/hockey/team:23", "value": 7}, "anaheim_ducks": {"team_key": "/sport/hockey/team:25", "value": 21}}}, "Montgomery (Selma) AL": {"min_value": 2, "values": {"vancouver_canucks": {"team_key": "/sport/hockey/team:26", "value": 2}, "montreal_canadiens": {"team_key": "/sport/hockey/team:11", "value": 2}, "toronto_maple_leafs": {"team_key": "/sport/hockey/team:8", "value": 10}, "washington_capitals": {"team_key": "/sport/hockey/team:15", "value": 2}, "nashville_predators": {"team_key": "/sport/hockey/team:27", "value": 3}}}, "Juneau AK": {"min_value": 4, "values": {"vancouver_canucks": {"team_key": "/sport/hockey/team:26", "value": 20}, "san_jose_sharks": {"team_key": "/sport/hockey/team:21", "value": 7}, "los_angeles_kings": {"team_key": "/sport/hockey/team:23", "value": 6}, "detroit_red_wings": {"team_key": "/sport/hockey/team:2", "value": 4}, "columbus_blue_jackets": {"team_key": "/sport/hockey/team:30", "value": 100}}}, "Traverse City-Cadillac MI": {"min_value": 14, "values": {"montreal_canadiens": {"team_key": "/sport/hockey/team:11", "value": 14}, "toronto_maple_leafs": {"team_key": "/sport/hockey/team:8", "value": 45}, "detroit_red_wings": {"team_key": "/sport/hockey/team:2", "value": 58}, "edmonton_oilers": {"team_key": "/sport/hockey/team:24", "value": 20}, "winnipeg_jets": {"team_key": "/sport/hockey/team:28", "value": 20}}}, "Sioux City IA": {"min_value": 7, "values": {"winnipeg_jets": {"team_key": "/sport/hockey/team:28", "value": 9}, "toronto_maple_leafs": {"team_key": "/sport/hockey/team:8", "value": 15}, "minnesota_wild": {"team_key": "/sport/hockey/team:29", "value": 7}, "edmonton_oilers": {"team_key": "/sport/hockey/team:24", "value": 18}, "anaheim_ducks": {"team_key": "/sport/hockey/team:25", "value": 9}}}, "El Paso TX": {"min_value": 4, "values": {"los_angeles_kings": {"team_key": "/sport/hockey/team:23", "value": 5}, "arizona_coyotes": {"team_key": "/sport/hockey/team:19", "value": 4}, "dallas_stars": {"team_key": "/sport/hockey/team:20", "value": 6}, "toronto_maple_leafs": {"team_key": "/sport/hockey/team:8", "value": 14}, "anaheim_ducks": {"team_key": "/sport/hockey/team:25", "value": 5}}}, "New York NY": {"min_value": 18, "values": {"new_jersey_devils": {"team_key": "/sport/hockey/team:13", "value": 100}, "new_york_islanders": {"team_key": "/sport/hockey/team:4", "value": 100}, "new_york_rangers": {"team_key": "/sport/hockey/team:6", "value": 100}, "toronto_maple_leafs": {"team_key": "/sport/hockey/team:8", "value": 26}, "edmonton_oilers": {"team_key": "/sport/hockey/team:24", "value": 18}}}, "Corpus Christi TX": {"min_value": 2, "values": {"vancouver_canucks": {"team_key": "/sport/hockey/team:26", "value": 2}, "new_york_islanders": {"team_key": "/sport/hockey/team:4", "value": 21}, "dallas_stars": {"team_key": "/sport/hockey/team:20", "value": 13}, "toronto_maple_leafs": {"team_key": "/sport/hockey/team:8", "value": 14}, "montreal_canadiens": {"team_key": "/sport/hockey/team:11", "value": 4}}}, "Indianapolis IN": {"min_value": 6, "values": {"chicago_blackhawks": {"team_key": "/sport/hockey/team:22", "value": 11}, "calgary_flames": {"team_key": "/sport/hockey/team:18", "value": 6}, "toronto_maple_leafs": {"team_key": "/sport/hockey/team:8", "value": 21}, "edmonton_oilers": {"team_key": "/sport/hockey/team:24", "value": 10}, "winnipeg_jets": {"team_key": "/sport/hockey/team:28", "value": 7}}}, "Lansing MI": {"min_value": 11, "values": {"montreal_canadiens": {"team_key": "/sport/hockey/team:11", "value": 11}, "toronto_maple_leafs": {"team_key": "/sport/hockey/team:8", "value": 34}, "detroit_red_wings": {"team_key": "/sport/hockey/team:2", "value": 54}, "edmonton_oilers": {"team_key": "/sport/hockey/team:24", "value": 15}, "winnipeg_jets": {"team_key": "/sport/hockey/team:28", "value": 18}}}, "Madison WI": {"min_value": 7, "values": {"chicago_blackhawks": {"team_key": "/sport/hockey/team:22", "value": 15}, "montreal_canadiens": {"team_key": "/sport/hockey/team:11", "value": 9}, "toronto_maple_leafs": {"team_key": "/sport/hockey/team:8", "value": 20}, "edmonton_oilers": {"team_key": "/sport/hockey/team:24", "value": 13}, "anaheim_ducks": {"team_key": "/sport/hockey/team:25", "value": 7}}}, "Columbia SC": {"min_value": 4, "values": {"new_jersey_devils": {"team_key": "/sport/hockey/team:13", "value": 5}, "carolina_hurricanes": {"team_key": "/sport/hockey/team:5", "value": 7}, "montreal_canadiens": {"team_key": "/sport/hockey/team:11", "value": 5}, "toronto_maple_leafs": {"team_key": "/sport/hockey/team:8", "value": 16}, "winnipeg_jets": {"team_key": "/sport/hockey/team:28", "value": 4}}}, "Mobile AL-Pensacola (Ft. Walton Beach) FL": {"min_value": 4, "values": {"vancouver_canucks": {"team_key": "/sport/hockey/team:26", "value": 4}, "montreal_canadiens": {"team_key": "/sport/hockey/team:11", "value": 6}, "toronto_maple_leafs": {"team_key": "/sport/hockey/team:8", "value": 13}, "edmonton_oilers": {"team_key": "/sport/hockey/team:24", "value": 7}, "tampa_bay_lightning": {"team_key": "/sport/hockey/team:17", "value": 4}}}, "Tallahassee FL-Thomasville GA": {"min_value": 5, "values": {"calgary_flames": {"team_key": "/sport/hockey/team:18", "value": 5}, "toronto_maple_leafs": {"team_key": "/sport/hockey/team:8", "value": 14}, "florida_panthers": {"team_key": "/sport/hockey/team:14", "value": 16}, "tampa_bay_lightning": {"team_key": "/sport/hockey/team:17", "value": 11}, "winnipeg_jets": {"team_key": "/sport/hockey/team:28", "value": 6}}}, "Roanoke-Lynchburg VA": {"min_value": 3, "values": {"new_jersey_devils": {"team_key": "/sport/hockey/team:13", "value": 3}, "calgary_flames": {"team_key": "/sport/hockey/team:18", "value": 5}, "new_york_islanders": {"team_key": "/sport/hockey/team:4", "value": 4}, "toronto_maple_leafs": {"team_key": "/sport/hockey/team:8", "value": 9}, "washington_capitals": {"team_key": "/sport/hockey/team:15", "value": 8}}}, "Miami-Ft. Lauderdale FL": {"min_value": 8, "values": {"new_york_islanders": {"team_key": "/sport/hockey/team:4", "value": 8}, "montreal_canadiens": {"team_key": "/sport/hockey/team:11", "value": 13}, "toronto_maple_leafs": {"team_key": "/sport/hockey/team:8", "value": 23}, "florida_panthers": {"team_key": "/sport/hockey/team:14", "value": 96}, "tampa_bay_lightning": {"team_key": "/sport/hockey/team:17", "value": 9}}}, "Duluth MN-Superior WI": {"min_value": 24, "values": {"calgary_flames": {"team_key": "/sport/hockey/team:18", "value": 24}, "toronto_maple_leafs": {"team_key": "/sport/hockey/team:8", "value": 36}, "minnesota_wild": {"team_key": "/sport/hockey/team:29", "value": 100}, "edmonton_oilers": {"team_key": "/sport/hockey/team:24", "value": 37}, "winnipeg_jets": {"team_key": "/sport/hockey/team:28", "value": 33}}}, "Monroe LA-El Dorado AR": {"min_value": 1, "values": {"chicago_blackhawks": {"team_key": "/sport/hockey/team:22", "value": 1}, "st._louis_blues": {"team_key": "/sport/hockey/team:16", "value": 1}, "dallas_stars": {"team_key": "/sport/hockey/team:20", "value": 8}, "new_york_rangers": {"team_key": "/sport/hockey/team:6", "value": 1}, "los_angeles_kings": {"team_key": "/sport/hockey/team:23", "value": 2}}}, "Peoria-Bloomington IL": {"min_value": 12, "values": {"chicago_blackhawks": {"team_key": "/sport/hockey/team:22", "value": 40}, "calgary_flames": {"team_key": "/sport/hockey/team:18", "value": 13}, "toronto_maple_leafs": {"team_key": "/sport/hockey/team:8", "value": 17}, "edmonton_oilers": {"team_key": "/sport/hockey/team:24", "value": 16}, "winnipeg_jets": {"team_key": "/sport/hockey/team:28", "value": 12}}}, "Phoenix AZ": {"min_value": 14, "values": {"arizona_coyotes": {"team_key": "/sport/hockey/team:19", "value": 100}, "calgary_flames": {"team_key": "/sport/hockey/team:18", "value": 17}, "toronto_maple_leafs": {"team_key": "/sport/hockey/team:8", "value": 21}, "edmonton_oilers": {"team_key": "/sport/hockey/team:24", "value": 28}, "winnipeg_jets": {"team_key": "/sport/hockey/team:28", "value": 14}}}, "Pittsburgh PA": {"min_value": 20, "values": {"new_york_islanders": {"team_key": "/sport/hockey/team:4", "value": 20}, "toronto_maple_leafs": {"team_key": "/sport/hockey/team:8", "value": 40}, "pittsburgh_penguins": {"team_key": "/sport/hockey/team:7", "value": 100}, "edmonton_oilers": {"team_key": "/sport/hockey/team:24", "value": 34}, "winnipeg_jets": {"team_key": "/sport/hockey/team:28", "value": 21}}}, "Nashville TN": {"min_value": 7, "values": {"nashville_predators": {"team_key": "/sport/hockey/team:27", "value": 100}, "winnipeg_jets": {"team_key": "/sport/hockey/team:28", "value": 7}, "toronto_maple_leafs": {"team_key": "/sport/hockey/team:8", "value": 16}, "edmonton_oilers": {"team_key": "/sport/hockey/team:24", "value": 15}, "anaheim_ducks": {"team_key": "/sport/hockey/team:25", "value": 7}}}, "Syracuse NY": {"min_value": 21, "values": {"new_jersey_devils": {"team_key": "/sport/hockey/team:13", "value": 21}, "new_york_islanders": {"team_key": "/sport/hockey/team:4", "value": 29}, "new_york_rangers": {"team_key": "/sport/hockey/team:6", "value": 41}, "toronto_maple_leafs": {"team_key": "/sport/hockey/team:8", "value": 41}, "montreal_canadiens": {"team_key": "/sport/hockey/team:11", "value": 24}}}, "Dayton OH": {"min_value": 4, "values": {"columbus_blue_jackets": {"team_key": "/sport/hockey/team:30", "value": 19}, "toronto_maple_leafs": {"team_key": "/sport/hockey/team:8", "value": 21}, "detroit_red_wings": {"team_key": "/sport/hockey/team:2", "value": 4}, "edmonton_oilers": {"team_key": "/sport/hockey/team:24", "value": 11}, "anaheim_ducks": {"team_key": "/sport/hockey/team:25", "value": 4}}}, "Cincinnati OH": {"min_value": 6, "values": {"columbus_blue_jackets": {"team_key": "/sport/hockey/team:30", "value": 12}, "montreal_canadiens": {"team_key": "/sport/hockey/team:11", "value": 6}, "toronto_maple_leafs": {"team_key": "/sport/hockey/team:8", "value": 19}, "edmonton_oilers": {"team_key": "/sport/hockey/team:24", "value": 13}, "winnipeg_jets": {"team_key": "/sport/hockey/team:28", "value": 6}}}, "Monterey-Salinas CA": {"min_value": 8, "values": {"los_angeles_kings": {"team_key": "/sport/hockey/team:23", "value": 11}, "vancouver_canucks": {"team_key": "/sport/hockey/team:26", "value": 8}, "san_jose_sharks": {"team_key": "/sport/hockey/team:21", "value": 100}, "toronto_maple_leafs": {"team_key": "/sport/hockey/team:8", "value": 24}, "anaheim_ducks": {"team_key": "/sport/hockey/team:25", "value": 13}}}, "Albany-Schenectady-Troy NY": {"min_value": 22, "values": {"new_jersey_devils": {"team_key": "/sport/hockey/team:13", "value": 39}, "new_york_islanders": {"team_key": "/sport/hockey/team:4", "value": 28}, "new_york_rangers": {"team_key": "/sport/hockey/team:6", "value": 49}, "toronto_maple_leafs": {"team_key": "/sport/hockey/team:8", "value": 29}, "montreal_canadiens": {"team_key": "/sport/hockey/team:11", "value": 22}}}, "Charlotte NC": {"min_value": 7, "values": {"new_jersey_devils": {"team_key": "/sport/hockey/team:13", "value": 7}, "carolina_hurricanes": {"team_key": "/sport/hockey/team:5", "value": 19}, "new_york_islanders": {"team_key": "/sport/hockey/team:4", "value": 7}, "toronto_maple_leafs": {"team_key": "/sport/hockey/team:8", "value": 16}, "edmonton_oilers": {"team_key": "/sport/hockey/team:24", "value": 10}}}, "Albuquerque-Santa Fe NM": {"min_value": 6, "values": {"calgary_flames": {"team_key": "/sport/hockey/team:18", "value": 6}, "colorado_avalanche": {"team_key": "/sport/hockey/team:1", "value": 7}, "toronto_maple_leafs": {"team_key": "/sport/hockey/team:8", "value": 16}, "edmonton_oilers": {"team_key": "/sport/hockey/team:24", "value": 8}, "winnipeg_jets": {"team_key": "/sport/hockey/team:28", "value": 6}}}, "Honolulu HI": {"min_value": 22, "values": {"calgary_flames": {"team_key": "/sport/hockey/team:18", "value": 22}, "vancouver_canucks": {"team_key": "/sport/hockey/team:26", "value": 31}, "toronto_maple_leafs": {"team_key": "/sport/hockey/team:8", "value": 22}, "edmonton_oilers": {"team_key": "/sport/hockey/team:24", "value": 29}, "anaheim_ducks": {"team_key": "/sport/hockey/team:25", "value": 32}}}, "Norfolk-Portsmouth-Newport News VA": {"min_value": 7, "values": {"new_jersey_devils": {"team_key": "/sport/hockey/team:13", "value": 7}, "toronto_maple_leafs": {"team_key": "/sport/hockey/team:8", "value": 15}, "washington_capitals": {"team_key": "/sport/hockey/team:15", "value": 20}, "edmonton_oilers": {"team_key": "/sport/hockey/team:24", "value": 11}, "anaheim_ducks": {"team_key": "/sport/hockey/team:25", "value": 7}}}, "Fargo-Valley City ND": {"min_value": 24, "values": {"calgary_flames": {"team_key": "/sport/hockey/team:18", "value": 24}, "toronto_maple_leafs": {"team_key": "/sport/hockey/team:8", "value": 33}, "minnesota_wild": {"team_key": "/sport/hockey/team:29", "value": 54}, "edmonton_oilers": {"team_key": "/sport/hockey/team:24", "value": 31}, "winnipeg_jets": {"team_key": "/sport/hockey/team:28", "value": 100}}}, "Charleston-Huntington WV": {"min_value": 4, "values": {"new_jersey_devils": {"team_key": "/sport/hockey/team:13", "value": 5}, "chicago_blackhawks": {"team_key": "/sport/hockey/team:22", "value": 4}, "columbus_blue_jackets": {"team_key": "/sport/hockey/team:30", "value": 5}, "toronto_maple_leafs": {"team_key": "/sport/hockey/team:8", "value": 18}, "washington_capitals": {"team_key": "/sport/hockey/team:15", "value": 5}}}, "Great Falls Mount": {"min_value": 4, "values": {"los_angeles_kings": {"team_key": "/sport/hockey/team:23", "value": 6}, "colorado_avalanche": {"team_key": "/sport/hockey/team:1", "value": 9}, "san_jose_sharks": {"team_key": "/sport/hockey/team:21", "value": 4}, "calgary_flames": {"team_key": "/sport/hockey/team:18", "value": 70}, "anaheim_ducks": {"team_key": "/sport/hockey/team:25", "value": 9}}}, "Birmingham AL": {"min_value": 3, "values": {"new_jersey_devils": {"team_key": "/sport/hockey/team:13", "value": 4}, "vancouver_canucks": {"team_key": "/sport/hockey/team:26", "value": 3}, "toronto_maple_leafs": {"team_key": "/sport/hockey/team:8", "value": 9}, "edmonton_oilers": {"team_key": "/sport/hockey/team:24", "value": 6}, "nashville_predators": {"team_key": "/sport/hockey/team:27", "value": 6}}}, "Bluefield-Beckley-Oak Hill WV": {"min_value": 1, "values": {"chicago_blackhawks": {"team_key": "/sport/hockey/team:22", "value": 2}, "boston_bruins": {"team_key": "/sport/hockey/team:3", "value": 1}, "washington_capitals": {"team_key": "/sport/hockey/team:15", "value": 6}, "pittsburgh_penguins": {"team_key": "/sport/hockey/team:7", "value": 2}, "florida_panthers": {"team_key": "/sport/hockey/team:14", "value": 7}}}, "Eugene OR": {"min_value": 5, "values": {"los_angeles_kings": {"team_key": "/sport/hockey/team:23", "value": 5}, "vancouver_canucks": {"team_key": "/sport/hockey/team:26", "value": 11}, "san_jose_sharks": {"team_key": "/sport/hockey/team:21", "value": 7}, "toronto_maple_leafs": {"team_key": "/sport/hockey/team:8", "value": 22}, "anaheim_ducks": {"team_key": "/sport/hockey/team:25", "value": 27}}}, "New Orleans LA": {"min_value": 4, "values": {"new_york_rangers": {"team_key": "/sport/hockey/team:6", "value": 4}, "dallas_stars": {"team_key": "/sport/hockey/team:20", "value": 6}, "toronto_maple_leafs": {"team_key": "/sport/hockey/team:8", "value": 12}, "edmonton_oilers": {"team_key": "/sport/hockey/team:24", "value": 12}, "montreal_canadiens": {"team_key": "/sport/hockey/team:11", "value": 4}}}, "Detroit MI": {"min_value": 14, "values": {"montreal_canadiens": {"team_key": "/sport/hockey/team:11", "value": 14}, "toronto_maple_leafs": {"team_key": "/sport/hockey/team:8", "value": 51}, "detroit_red_wings": {"team_key": "/sport/hockey/team:2", "value": 72}, "edmonton_oilers": {"team_key": "/sport/hockey/team:24", "value": 22}, "winnipeg_jets": {"team_key": "/sport/hockey/team:28", "value": 14}}}, "Hattiesburg-Laurel MS": {"min_value": 1, "values": {"chicago_blackhawks": {"team_key": "/sport/hockey/team:22", "value": 1}, "nashville_predators": {"team_key": "/sport/hockey/team:27", "value": 2}, "detroit_red_wings": {"team_key": "/sport/hockey/team:2", "value": 1}, "tampa_bay_lightning": {"team_key": "/sport/hockey/team:17", "value": 1}, "anaheim_ducks": {"team_key": "/sport/hockey/team:25", "value": 2}}}, "Medford-Klamath Falls OR": {"min_value": 6, "values": {"los_angeles_kings": {"team_key": "/sport/hockey/team:23", "value": 6}, "vancouver_canucks": {"team_key": "/sport/hockey/team:26", "value": 6}, "san_jose_sharks": {"team_key": "/sport/hockey/team:21", "value": 11}, "toronto_maple_leafs": {"team_key": "/sport/hockey/team:8", "value": 16}, "anaheim_ducks": {"team_key": "/sport/hockey/team:25", "value": 31}}}, "Davenport IA-Rock Island-Moline IL": {"min_value": 8, "values": {"chicago_blackhawks": {"team_key": "/sport/hockey/team:22", "value": 28}, "calgary_flames": {"team_key": "/sport/hockey/team:18", "value": 9}, "toronto_maple_leafs": {"team_key": "/sport/hockey/team:8", "value": 24}, "edmonton_oilers": {"team_key": "/sport/hockey/team:24", "value": 14}, "anaheim_ducks": {"team_key": "/sport/hockey/team:25", "value": 8}}}, "Charlottesville VA": {"min_value": 7, "values": {"new_jersey_devils": {"team_key": "/sport/hockey/team:13", "value": 8}, "vancouver_canucks": {"team_key": "/sport/hockey/team:26", "value": 7}, "montreal_canadiens": {"team_key": "/sport/hockey/team:11", "value": 8}, "toronto_maple_leafs": {"team_key": "/sport/hockey/team:8", "value": 16}, "washington_capitals": {"team_key": "/sport/hockey/team:15", "value": 34}}}, "Wilmington NC": {"min_value": 11, "values": {"carolina_hurricanes": {"team_key": "/sport/hockey/team:5", "value": 43}, "new_york_rangers": {"team_key": "/sport/hockey/team:6", "value": 12}, "toronto_maple_leafs": {"team_key": "/sport/hockey/team:8", "value": 15}, "washington_capitals": {"team_key": "/sport/hockey/team:15", "value": 11}, "edmonton_oilers": {"team_key": "/sport/hockey/team:24", "value": 12}}}, "Jackson TN": {"min_value": 1, "values": {"chicago_blackhawks": {"team_key": "/sport/hockey/team:22", "value": 2}, "boston_bruins": {"team_key": "/sport/hockey/team:3", "value": 1}, "nashville_predators": {"team_key": "/sport/hockey/team:27", "value": 33}, "detroit_red_wings": {"team_key": "/sport/hockey/team:2", "value": 1}, "st._louis_blues": {"team_key": "/sport/hockey/team:16", "value": 1}}}, "West Palm Beach-Ft. Pierce FL": {"min_value": 11, "values": {"new_york_islanders": {"team_key": "/sport/hockey/team:4", "value": 11}, "new_york_rangers": {"team_key": "/sport/hockey/team:6", "value": 12}, "toronto_maple_leafs": {"team_key": "/sport/hockey/team:8", "value": 29}, "florida_panthers": {"team_key": "/sport/hockey/team:14", "value": 100}, "montreal_canadiens": {"team_key": "/sport/hockey/team:11", "value": 16}}}, "Evansville IN": {"min_value": 4, "values": {"calgary_flames": {"team_key": "/sport/hockey/team:18", "value": 5}, "vancouver_canucks": {"team_key": "/sport/hockey/team:26", "value": 4}, "toronto_maple_leafs": {"team_key": "/sport/hockey/team:8", "value": 18}, "edmonton_oilers": {"team_key": "/sport/hockey/team:24", "value": 17}, "nashville_predators": {"team_key": "/sport/hockey/team:27", "value": 11}}}, "Wilkes Barre-Scranton PA": {"min_value": 14, "values": {"new_jersey_devils": {"team_key": "/sport/hockey/team:13", "value": 27}, "toronto_maple_leafs": {"team_key": "/sport/hockey/team:8", "value": 24}, "new_york_islanders": {"team_key": "/sport/hockey/team:4", "value": 14}, "new_york_rangers": {"team_key": "/sport/hockey/team:6", "value": 21}, "philadelphia_flyers": {"team_key": "/sport/hockey/team:12", "value": 24}}}, "St. Louis MO": {"min_value": 12, "values": {"calgary_flames": {"team_key": "/sport/hockey/team:18", "value": 12}, "st._louis_blues": {"team_key": "/sport/hockey/team:16", "value": 100}, "toronto_maple_leafs": {"team_key": "/sport/hockey/team:8", "value": 25}, "edmonton_oilers": {"team_key": "/sport/hockey/team:24", "value": 22}, "winnipeg_jets": {"team_key": "/sport/hockey/team:28", "value": 14}}}, "Providence RI-New Bedford MA": {"min_value": 16, "values": {"boston_bruins": {"team_key": "/sport/hockey/team:3", "value": 70}, "new_york_islanders": {"team_key": "/sport/hockey/team:4", "value": 16}, "montreal_canadiens": {"team_key": "/sport/hockey/team:11", "value": 29}, "toronto_maple_leafs": {"team_key": "/sport/hockey/team:8", "value": 37}, "edmonton_oilers": {"team_key": "/sport/hockey/team:24", "value": 20}}}, "Mankato MN": {"min_value": 11, "values": {"vancouver_canucks": {"team_key": "/sport/hockey/team:26", "value": 11}, "calgary_flames": {"team_key": "/sport/hockey/team:18", "value": 40}, "minnesota_wild": {"team_key": "/sport/hockey/team:29", "value": 100}, "edmonton_oilers": {"team_key": "/sport/hockey/team:24", "value": 49}, "winnipeg_jets": {"team_key": "/sport/hockey/team:28", "value": 21}}}, "Harrisburg-Lancaster-Lebanon-York PA": {"min_value": 19, "values": {"new_jersey_devils": {"team_key": "/sport/hockey/team:13", "value": 19}, "toronto_maple_leafs": {"team_key": "/sport/hockey/team:8", "value": 23}, "washington_capitals": {"team_key": "/sport/hockey/team:15", "value": 26}, "philadelphia_flyers": {"team_key": "/sport/hockey/team:12", "value": 34}, "ottawa_senators": {"team_key": "/sport/hockey/team:9", "value": 47}}}, "Columbus GA": {"min_value": 4, "values": {"calgary_flames": {"team_key": "/sport/hockey/team:18", "value": 4}, "montreal_canadiens": {"team_key": "/sport/hockey/team:11", "value": 6}, "toronto_maple_leafs": {"team_key": "/sport/hockey/team:8", "value": 7}, "florida_panthers": {"team_key": "/sport/hockey/team:14", "value": 4}, "anaheim_ducks": {"team_key": "/sport/hockey/team:25", "value": 6}}}, "Portland OR": {"min_value": 5, "values": {"calgary_flames": {"team_key": "/sport/hockey/team:18", "value": 5}, "vancouver_canucks": {"team_key": "/sport/hockey/team:26", "value": 8}, "toronto_maple_leafs": {"team_key": "/sport/hockey/team:8", "value": 13}, "edmonton_oilers": {"team_key": "/sport/hockey/team:24", "value": 8}, "anaheim_ducks": {"team_key": "/sport/hockey/team:25", "value": 10}}}, "Toledo OH": {"min_value": 7, "values": {"columbus_blue_jackets": {"team_key": "/sport/hockey/team:30", "value": 11}, "toronto_maple_leafs": {"team_key": "/sport/hockey/team:8", "value": 32}, "detroit_red_wings": {"team_key": "/sport/hockey/team:2", "value": 21}, "edmonton_oilers": {"team_key": "/sport/hockey/team:24", "value": 22}, "anaheim_ducks": {"team_key": "/sport/hockey/team:25", "value": 7}}}, "Anchorage AK": {"min_value": 14, "values": {"calgary_flames": {"team_key": "/sport/hockey/team:18", "value": 14}, "vancouver_canucks": {"team_key": "/sport/hockey/team:26", "value": 14}, "toronto_maple_leafs": {"team_key": "/sport/hockey/team:8", "value": 22}, "edmonton_oilers": {"team_key": "/sport/hockey/team:24", "value": 55}, "anaheim_ducks": {"team_key": "/sport/hockey/team:25", "value": 14}}}, "Lafayette IN": {"min_value": 3, "values": {"chicago_blackhawks": {"team_key": "/sport/hockey/team:22", "value": 17}, "vancouver_canucks": {"team_key": "/sport/hockey/team:26", "value": 11}, "montreal_canadiens": {"team_key": "/sport/hockey/team:11", "value": 6}, "detroit_red_wings": {"team_key": "/sport/hockey/team:2", "value": 3}, "anaheim_ducks": {"team_key": "/sport/hockey/team:25", "value": 8}}}, "Paducah KY-Cape Girardeau MO-Harrisburg-Mount Vernon IL": {"min_value": 8, "values": {"calgary_flames": {"team_key": "/sport/hockey/team:18", "value": 8}, "st._louis_blues": {"team_key": "/sport/hockey/team:16", "value": 25}, "toronto_maple_leafs": {"team_key": "/sport/hockey/team:8", "value": 18}, "edmonton_oilers": {"team_key": "/sport/hockey/team:24", "value": 13}, "nashville_predators": {"team_key": "/sport/hockey/team:27", "value": 12}}}, "Utica NY": {"min_value": 38, "values": {"new_jersey_devils": {"team_key": "/sport/hockey/team:13", "value": 38}, "vancouver_canucks": {"team_key": "/sport/hockey/team:26", "value": 45}, "new_york_islanders": {"team_key": "/sport/hockey/team:4", "value": 54}, "new_york_rangers": {"team_key": "/sport/hockey/team:6", "value": 70}, "toronto_maple_leafs": {"team_key": "/sport/hockey/team:8", "value": 54}}}, "Hartford & New Haven CT": {"min_value": 20, "values": {"boston_bruins": {"team_key": "/sport/hockey/team:3", "value": 20}, "new_york_islanders": {"team_key": "/sport/hockey/team:4", "value": 24}, "new_york_rangers": {"team_key": "/sport/hockey/team:6", "value": 35}, "toronto_maple_leafs": {"team_key": "/sport/hockey/team:8", "value": 28}, "montreal_canadiens": {"team_key": "/sport/hockey/team:11", "value": 21}}}, "Joplin MO-Pittsburg KS": {"min_value": 3, "values": {"vancouver_canucks": {"team_key": "/sport/hockey/team:26", "value": 3}, "san_jose_sharks": {"team_key": "/sport/hockey/team:21", "value": 3}, "montreal_canadiens": {"team_key": "/sport/hockey/team:11", "value": 3}, "toronto_maple_leafs": {"team_key": "/sport/hockey/team:8", "value": 20}, "st._louis_blues": {"team_key": "/sport/hockey/team:16", "value": 5}}}, "Cheyenne WY-Scottsbluff NE": {"min_value": 3, "values": {"colorado_avalanche": {"team_key": "/sport/hockey/team:1", "value": 44}, "san_jose_sharks": {"team_key": "/sport/hockey/team:21", "value": 4}, "montreal_canadiens": {"team_key": "/sport/hockey/team:11", "value": 7}, "anaheim_ducks": {"team_key": "/sport/hockey/team:25", "value": 3}, "vancouver_canucks": {"team_key": "/sport/hockey/team:26", "value": 4}}}, "Lexington KY": {"min_value": 5, "values": {"calgary_flames": {"team_key": "/sport/hockey/team:18", "value": 5}, "nashville_predators": {"team_key": "/sport/hockey/team:27", "value": 6}, "toronto_maple_leafs": {"team_key": "/sport/hockey/team:8", "value": 18}, "edmonton_oilers": {"team_key": "/sport/hockey/team:24", "value": 8}, "winnipeg_jets": {"team_key": "/sport/hockey/team:28", "value": 6}}}, "Dallas-Ft. Worth TX": {"min_value": 5, "values": {"vancouver_canucks": {"team_key": "/sport/hockey/team:26", "value": 5}, "dallas_stars": {"team_key": "/sport/hockey/team:20", "value": 100}, "toronto_maple_leafs": {"team_key": "/sport/hockey/team:8", "value": 16}, "edmonton_oilers": {"team_key": "/sport/hockey/team:24", "value": 16}, "anaheim_ducks": {"team_key": "/sport/hockey/team:25", "value": 5}}}, "Binghamton NY": {"min_value": 25, "values": {"new_jersey_devils": {"team_key": "/sport/hockey/team:13", "value": 25}, "new_york_islanders": {"team_key": "/sport/hockey/team:4", "value": 38}, "new_york_rangers": {"team_key": "/sport/hockey/team:6", "value": 66}, "toronto_maple_leafs": {"team_key": "/sport/hockey/team:8", "value": 31}, "ottawa_senators": {"team_key": "/sport/hockey/team:9", "value": 75}}}, "Billings, Mount": {"min_value": 5, "values": {"los_angeles_kings": {"team_key": "/sport/hockey/team:23", "value": 5}, "vancouver_canucks": {"team_key": "/sport/hockey/team:26", "value": 5}, "montreal_canadiens": {"team_key": "/sport/hockey/team:11", "value": 8}, "calgary_flames": {"team_key": "/sport/hockey/team:18", "value": 14}, "colorado_avalanche": {"team_key": "/sport/hockey/team:1", "value": 18}}}, "Charleston SC": {"min_value": 7, "values": {"carolina_hurricanes": {"team_key": "/sport/hockey/team:5", "value": 8}, "new_york_islanders": {"team_key": "/sport/hockey/team:4", "value": 7}, "new_york_rangers": {"team_key": "/sport/hockey/team:6", "value": 7}, "toronto_maple_leafs": {"team_key": "/sport/hockey/team:8", "value": 15}, "montreal_canadiens": {"team_key": "/sport/hockey/team:11", "value": 7}}}, "Denver CO": {"min_value": 11, "values": {"calgary_flames": {"team_key": "/sport/hockey/team:18", "value": 11}, "colorado_avalanche": {"team_key": "/sport/hockey/team:1", "value": 100}, "toronto_maple_leafs": {"team_key": "/sport/hockey/team:8", "value": 21}, "edmonton_oilers": {"team_key": "/sport/hockey/team:24", "value": 17}, "winnipeg_jets": {"team_key": "/sport/hockey/team:28", "value": 12}}}, "Biloxi-Gulfport MS": {"min_value": 2, "values": {"boston_bruins": {"team_key": "/sport/hockey/team:3", "value": 2}, "new_york_islanders": {"team_key": "/sport/hockey/team:4", "value": 5}, "dallas_stars": {"team_key": "/sport/hockey/team:20", "value": 3}, "los_angeles_kings": {"team_key": "/sport/hockey/team:23", "value": 3}, "anaheim_ducks": {"team_key": "/sport/hockey/team:25", "value": 3}}}, "Austin TX": {"min_value": 5, "values": {"vancouver_canucks": {"team_key": "/sport/hockey/team:26", "value": 5}, "dallas_stars": {"team_key": "/sport/hockey/team:20", "value": 19}, "toronto_maple_leafs": {"team_key": "/sport/hockey/team:8", "value": 17}, "edmonton_oilers": {"team_key": "/sport/hockey/team:24", "value": 18}, "anaheim_ducks": {"team_key": "/sport/hockey/team:25", "value": 5}}}, "San Francisco-Oakland-San Jose CA": {"min_value": 13, "values": {"los_angeles_kings": {"team_key": "/sport/hockey/team:23", "value": 13}, "san_jose_sharks": {"team_key": "/sport/hockey/team:21", "value": 97}, "toronto_maple_leafs": {"team_key": "/sport/hockey/team:8", "value": 19}, "edmonton_oilers": {"team_key": "/sport/hockey/team:24", "value": 14}, "anaheim_ducks": {"team_key": "/sport/hockey/team:25", "value": 13}}}, "Marquette MI": {"min_value": 20, "values": {"calgary_flames": {"team_key": "/sport/hockey/team:18", "value": 33}, "winnipeg_jets": {"team_key": "/sport/hockey/team:28", "value": 21}, "toronto_maple_leafs": {"team_key": "/sport/hockey/team:8", "value": 63}, "detroit_red_wings": {"team_key": "/sport/hockey/team:2", "value": 78}, "anaheim_ducks": {"team_key": "/sport/hockey/team:25", "value": 20}}}, "Wichita-Hutchinson KS": {"min_value": 5, "values": {"calgary_flames": {"team_key": "/sport/hockey/team:18", "value": 5}, "montreal_canadiens": {"team_key": "/sport/hockey/team:11", "value": 5}, "toronto_maple_leafs": {"team_key": "/sport/hockey/team:8", "value": 14}, "edmonton_oilers": {"team_key": "/sport/hockey/team:24", "value": 15}, "winnipeg_jets": {"team_key": "/sport/hockey/team:28", "value": 6}}}, "Florence-Myrtle Beach SC": {"min_value": 8, "values": {"carolina_hurricanes": {"team_key": "/sport/hockey/team:5", "value": 11}, "new_york_rangers": {"team_key": "/sport/hockey/team:6", "value": 8}, "toronto_maple_leafs": {"team_key": "/sport/hockey/team:8", "value": 27}, "edmonton_oilers": {"team_key": "/sport/hockey/team:24", "value": 9}, "montreal_canadiens": {"team_key": "/sport/hockey/team:11", "value": 8}}}, "Rockford IL": {"min_value": 10, "values": {"chicago_blackhawks": {"team_key": "/sport/hockey/team:22", "value": 61}, "montreal_canadiens": {"team_key": "/sport/hockey/team:11", "value": 10}, "toronto_maple_leafs": {"team_key": "/sport/hockey/team:8", "value": 26}, "edmonton_oilers": {"team_key": "/sport/hockey/team:24", "value": 20}, "anaheim_ducks": {"team_key": "/sport/hockey/team:25", "value": 14}}}, "Oklahoma City OK": {"min_value": 10, "values": {"dallas_stars": {"team_key": "/sport/hockey/team:20", "value": 14}, "toronto_maple_leafs": {"team_key": "/sport/hockey/team:8", "value": 14}, "florida_panthers": {"team_key": "/sport/hockey/team:14", "value": 11}, "tampa_bay_lightning": {"team_key": "/sport/hockey/team:17", "value": 10}, "edmonton_oilers": {"team_key": "/sport/hockey/team:24", "value": 24}}}, "Eureka CA": {"min_value": 7, "values": {"los_angeles_kings": {"team_key": "/sport/hockey/team:23", "value": 7}, "vancouver_canucks": {"team_key": "/sport/hockey/team:26", "value": 9}, "san_jose_sharks": {"team_key": "/sport/hockey/team:21", "value": 30}, "toronto_maple_leafs": {"team_key": "/sport/hockey/team:8", "value": 19}, "anaheim_ducks": {"team_key": "/sport/hockey/team:25", "value": 10}}}, "Little Rock-Pine Bluff AR": {"min_value": 3, "values": {"new_jersey_devils": {"team_key": "/sport/hockey/team:13", "value": 3}, "dallas_stars": {"team_key": "/sport/hockey/team:20", "value": 7}, "toronto_maple_leafs": {"team_key": "/sport/hockey/team:8", "value": 11}, "edmonton_oilers": {"team_key": "/sport/hockey/team:24", "value": 6}, "anaheim_ducks": {"team_key": "/sport/hockey/team:25", "value": 3}}}, "Waco-Temple-Bryan TX": {"min_value": 4, "values": {"vancouver_canucks": {"team_key": "/sport/hockey/team:26", "value": 4}, "dallas_stars": {"team_key": "/sport/hockey/team:20", "value": 28}, "toronto_maple_leafs": {"team_key": "/sport/hockey/team:8", "value": 12}, "edmonton_oilers": {"team_key": "/sport/hockey/team:24", "value": 13}, "winnipeg_jets": {"team_key": "/sport/hockey/team:28", "value": 5}}}, "\u0410\u043b\u043f\u0435\u043d\u0430": {"min_value": 3, "values": {"boston_bruins": {"team_key": "/sport/hockey/team:3", "value": 3}, "detroit_red_wings": {"team_key": "/sport/hockey/team:2", "value": 100}, "philadelphia_flyers": {"team_key": "/sport/hockey/team:12", "value": 14}}}, "Yakima-Pasco-Richland-Kennewick WA": {"min_value": 6, "values": {"calgary_flames": {"team_key": "/sport/hockey/team:18", "value": 7}, "vancouver_canucks": {"team_key": "/sport/hockey/team:26", "value": 16}, "montreal_canadiens": {"team_key": "/sport/hockey/team:11", "value": 6}, "toronto_maple_leafs": {"team_key": "/sport/hockey/team:8", "value": 22}, "anaheim_ducks": {"team_key": "/sport/hockey/team:25", "value": 6}}}, "Bangor ME": {"min_value": 17, "values": {"boston_bruins": {"team_key": "/sport/hockey/team:3", "value": 41}, "calgary_flames": {"team_key": "/sport/hockey/team:18", "value": 17}, "montreal_canadiens": {"team_key": "/sport/hockey/team:11", "value": 29}, "toronto_maple_leafs": {"team_key": "/sport/hockey/team:8", "value": 32}, "winnipeg_jets": {"team_key": "/sport/hockey/team:28", "value": 18}}}, "Minneapolis-St. Paul MN": {"min_value": 18, "values": {"calgary_flames": {"team_key": "/sport/hockey/team:18", "value": 18}, "toronto_maple_leafs": {"team_key": "/sport/hockey/team:8", "value": 30}, "minnesota_wild": {"team_key": "/sport/hockey/team:29", "value": 94}, "edmonton_oilers": {"team_key": "/sport/hockey/team:24", "value": 25}, "winnipeg_jets": {"team_key": "/sport/hockey/team:28", "value": 27}}}, "Terre Haute IN": {"min_value": 2, "values": {"chicago_blackhawks": {"team_key": "/sport/hockey/team:22", "value": 7}, "st._louis_blues": {"team_key": "/sport/hockey/team:16", "value": 6}, "new_york_rangers": {"team_key": "/sport/hockey/team:6", "value": 3}, "columbus_blue_jackets": {"team_key": "/sport/hockey/team:30", "value": 2}, "detroit_red_wings": {"team_key": "/sport/hockey/team:2", "value": 2}}}, "Macon GA": {"min_value": 2, "values": {"montreal_canadiens": {"team_key": "/sport/hockey/team:11", "value": 4}, "new_york_rangers": {"team_key": "/sport/hockey/team:6", "value": 4}, "toronto_maple_leafs": {"team_key": "/sport/hockey/team:8", "value": 5}, "florida_panthers": {"team_key": "/sport/hockey/team:14", "value": 3}, "anaheim_ducks": {"team_key": "/sport/hockey/team:25", "value": 2}}}, "Boston MA-Manchester NH": {"min_value": 19, "values": {"boston_bruins": {"team_key": "/sport/hockey/team:3", "value": 100}, "new_york_islanders": {"team_key": "/sport/hockey/team:4", "value": 19}, "montreal_canadiens": {"team_key": "/sport/hockey/team:11", "value": 35}, "toronto_maple_leafs": {"team_key": "/sport/hockey/team:8", "value": 41}, "edmonton_oilers": {"team_key": "/sport/hockey/team:24", "value": 26}}}, "Springfield MO": {"min_value": 4, "values": {"new_jersey_devils": {"team_key": "/sport/hockey/team:13", "value": 4}, "st._louis_blues": {"team_key": "/sport/hockey/team:16", "value": 16}, "toronto_maple_leafs": {"team_key": "/sport/hockey/team:8", "value": 18}, "edmonton_oilers": {"team_key": "/sport/hockey/team:24", "value": 10}, "anaheim_ducks": {"team_key": "/sport/hockey/team:25", "value": 4}}}, "South Bend-Elkhart IN": {"min_value": 7, "values": {"new_jersey_devils": {"team_key": "/sport/hockey/team:13", "value": 7}, "vancouver_canucks": {"team_key": "/sport/hockey/team:26", "value": 7}, "toronto_maple_leafs": {"team_key": "/sport/hockey/team:8", "value": 30}, "edmonton_oilers": {"team_key": "/sport/hockey/team:24", "value": 14}, "chicago_blackhawks": {"team_key": "/sport/hockey/team:22", "value": 19}}}, "Boise ID": {"min_value": 5, "values": {"vancouver_canucks": {"team_key": "/sport/hockey/team:26", "value": 6}, "san_jose_sharks": {"team_key": "/sport/hockey/team:21", "value": 5}, "toronto_maple_leafs": {"team_key": "/sport/hockey/team:8", "value": 16}, "edmonton_oilers": {"team_key": "/sport/hockey/team:24", "value": 10}, "anaheim_ducks": {"team_key": "/sport/hockey/team:25", "value": 8}}}, "Watertown NY": {"min_value": 44, "values": {"montreal_canadiens": {"team_key": "/sport/hockey/team:11", "value": 86}, "new_york_rangers": {"team_key": "/sport/hockey/team:6", "value": 58}, "toronto_maple_leafs": {"team_key": "/sport/hockey/team:8", "value": 100}, "ottawa_senators": {"team_key": "/sport/hockey/team:9", "value": 100}, "winnipeg_jets": {"team_key": "/sport/hockey/team:28", "value": 44}}}, "Johnstown-Altoona PA": {"min_value": 20, "values": {"new_jersey_devils": {"team_key": "/sport/hockey/team:13", "value": 20}, "toronto_maple_leafs": {"team_key": "/sport/hockey/team:8", "value": 40}, "philadelphia_flyers": {"team_key": "/sport/hockey/team:12", "value": 20}, "pittsburgh_penguins": {"team_key": "/sport/hockey/team:7", "value": 48}, "edmonton_oilers": {"team_key": "/sport/hockey/team:24", "value": 27}}}, "Jackson MS": {"min_value": 2, "values": {"los_angeles_kings": {"team_key": "/sport/hockey/team:23", "value": 2}, "calgary_flames": {"team_key": "/sport/hockey/team:18", "value": 3}, "dallas_stars": {"team_key": "/sport/hockey/team:20", "value": 2}, "toronto_maple_leafs": {"team_key": "/sport/hockey/team:8", "value": 7}, "montreal_canadiens": {"team_key": "/sport/hockey/team:11", "value": 4}}}, "Columbus OH": {"min_value": 8, "values": {"columbus_blue_jackets": {"team_key": "/sport/hockey/team:30", "value": 91}, "montreal_canadiens": {"team_key": "/sport/hockey/team:11", "value": 8}, "toronto_maple_leafs": {"team_key": "/sport/hockey/team:8", "value": 24}, "edmonton_oilers": {"team_key": "/sport/hockey/team:24", "value": 16}, "winnipeg_jets": {"team_key": "/sport/hockey/team:28", "value": 8}}}, "Greensboro-High Point-Winston Salem NC": {"min_value": 6, "values": {"new_jersey_devils": {"team_key": "/sport/hockey/team:13", "value": 9}, "carolina_hurricanes": {"team_key": "/sport/hockey/team:5", "value": 30}, "new_york_islanders": {"team_key": "/sport/hockey/team:4", "value": 6}, "toronto_maple_leafs": {"team_key": "/sport/hockey/team:8", "value": 14}, "edmonton_oilers": {"team_key": "/sport/hockey/team:24", "value": 9}}}, "Lafayette LA": {"min_value": 2, "values": {"vancouver_canucks": {"team_key": "/sport/hockey/team:26", "value": 3}, "montreal_canadiens": {"team_key": "/sport/hockey/team:11", "value": 3}, "new_york_rangers": {"team_key": "/sport/hockey/team:6", "value": 2}, "dallas_stars": {"team_key": "/sport/hockey/team:20", "value": 4}, "anaheim_ducks": {"team_key": "/sport/hockey/team:25", "value": 3}}}, "Washington DC (Hagerstown MD)": {"min_value": 12, "values": {"new_jersey_devils": {"team_key": "/sport/hockey/team:13", "value": 13}, "new_york_islanders": {"team_key": "/sport/hockey/team:4", "value": 14}, "new_york_rangers": {"team_key": "/sport/hockey/team:6", "value": 12}, "toronto_maple_leafs": {"team_key": "/sport/hockey/team:8", "value": 19}, "washington_capitals": {"team_key": "/sport/hockey/team:15", "value": 100}}}, "Rochester NY": {"min_value": 19, "values": {"buffalo_sabres": {"team_key": "/sport/hockey/team:10", "value": 22}, "new_york_rangers": {"team_key": "/sport/hockey/team:6", "value": 19}, "toronto_maple_leafs": {"team_key": "/sport/hockey/team:8", "value": 49}, "edmonton_oilers": {"team_key": "/sport/hockey/team:24", "value": 19}, "montreal_canadiens": {"team_key": "/sport/hockey/team:11", "value": 22}}}, "Augusta GA": {"min_value": 5, "values": {"new_jersey_devils": {"team_key": "/sport/hockey/team:13", "value": 5}, "new_york_rangers": {"team_key": "/sport/hockey/team:6", "value": 5}, "toronto_maple_leafs": {"team_key": "/sport/hockey/team:8", "value": 11}, "edmonton_oilers": {"team_key": "/sport/hockey/team:24", "value": 7}, "winnipeg_jets": {"team_key": "/sport/hockey/team:28", "value": 6}}}, "Flint-Saginaw-Bay City MI": {"min_value": 11, "values": {"calgary_flames": {"team_key": "/sport/hockey/team:18", "value": 11}, "toronto_maple_leafs": {"team_key": "/sport/hockey/team:8", "value": 33}, "detroit_red_wings": {"team_key": "/sport/hockey/team:2", "value": 55}, "edmonton_oilers": {"team_key": "/sport/hockey/team:24", "value": 29}, "winnipeg_jets": {"team_key": "/sport/hockey/team:28", "value": 12}}}, "Gainesville FL": {"min_value": 7, "values": {"new_jersey_devils": {"team_key": "/sport/hockey/team:13", "value": 9}, "new_york_islanders": {"team_key": "/sport/hockey/team:4", "value": 7}, "toronto_maple_leafs": {"team_key": "/sport/hockey/team:8", "value": 19}, "florida_panthers": {"team_key": "/sport/hockey/team:14", "value": 16}, "tampa_bay_lightning": {"team_key": "/sport/hockey/team:17", "value": 18}}}, "Cleveland-Akron (Canton) OH": {"min_value": 6, "values": {"columbus_blue_jackets": {"team_key": "/sport/hockey/team:30", "value": 12}, "montreal_canadiens": {"team_key": "/sport/hockey/team:11", "value": 7}, "toronto_maple_leafs": {"team_key": "/sport/hockey/team:8", "value": 21}, "edmonton_oilers": {"team_key": "/sport/hockey/team:24", "value": 10}, "winnipeg_jets": {"team_key": "/sport/hockey/team:28", "value": 6}}}, "Tyler-Longview(Lufkin & Nacogdoches) TX": {"min_value": 3, "values": {"vancouver_canucks": {"team_key": "/sport/hockey/team:26", "value": 3}, "dallas_stars": {"team_key": "/sport/hockey/team:20", "value": 35}, "toronto_maple_leafs": {"team_key": "/sport/hockey/team:8", "value": 11}, "edmonton_oilers": {"team_key": "/sport/hockey/team:24", "value": 7}, "anaheim_ducks": {"team_key": "/sport/hockey/team:25", "value": 4}}}, "Dothan AL": {"min_value": 1, "values": {"chicago_blackhawks": {"team_key": "/sport/hockey/team:22", "value": 2}, "boston_bruins": {"team_key": "/sport/hockey/team:3", "value": 1}, "nashville_predators": {"team_key": "/sport/hockey/team:27", "value": 2}, "los_angeles_kings": {"team_key": "/sport/hockey/team:23", "value": 2}, "tampa_bay_lightning": {"team_key": "/sport/hockey/team:17", "value": 2}}}, "Minot-Bismarck-Dickinson(Williston) ND": {"min_value": 15, "values": {"calgary_flames": {"team_key": "/sport/hockey/team:18", "value": 19}, "toronto_maple_leafs": {"team_key": "/sport/hockey/team:8", "value": 17}, "minnesota_wild": {"team_key": "/sport/hockey/team:29", "value": 15}, "edmonton_oilers": {"team_key": "/sport/hockey/team:24", "value": 43}, "winnipeg_jets": {"team_key": "/sport/hockey/team:28", "value": 34}}}, "Jacksonville FL": {"min_value": 6, "values": {"new_york_rangers": {"team_key": "/sport/hockey/team:6", "value": 6}, "toronto_maple_leafs": {"team_key": "/sport/hockey/team:8", "value": 14}, "florida_panthers": {"team_key": "/sport/hockey/team:14", "value": 11}, "tampa_bay_lightning": {"team_key": "/sport/hockey/team:17", "value": 7}, "edmonton_oilers": {"team_key": "/sport/hockey/team:24", "value": 10}}}, "Lake Charles LA": {"min_value": 1, "values": {"boston_bruins": {"team_key": "/sport/hockey/team:3", "value": 1}, "dallas_stars": {"team_key": "/sport/hockey/team:20", "value": 7}, "los_angeles_kings": {"team_key": "/sport/hockey/team:23", "value": 5}, "minnesota_wild": {"team_key": "/sport/hockey/team:29", "value": 2}, "tampa_bay_lightning": {"team_key": "/sport/hockey/team:17", "value": 1}}}, "Wausau-Rhinelander WI": {"min_value": 9, "values": {"chicago_blackhawks": {"team_key": "/sport/hockey/team:22", "value": 12}, "calgary_flames": {"team_key": "/sport/hockey/team:18", "value": 10}, "san_jose_sharks": {"team_key": "/sport/hockey/team:21", "value": 9}, "toronto_maple_leafs": {"team_key": "/sport/hockey/team:8", "value": 22}, "winnipeg_jets": {"team_key": "/sport/hockey/team:28", "value": 12}}}, "Green Bay-Appleton WI": {"min_value": 8, "values": {"chicago_blackhawks": {"team_key": "/sport/hockey/team:22", "value": 9}, "montreal_canadiens": {"team_key": "/sport/hockey/team:11", "value": 9}, "toronto_maple_leafs": {"team_key": "/sport/hockey/team:8", "value": 21}, "edmonton_oilers": {"team_key": "/sport/hockey/team:24", "value": 10}, "winnipeg_jets": {"team_key": "/sport/hockey/team:28", "value": 8}}}, "Salisbury MD": {"min_value": 10, "values": {"new_jersey_devils": {"team_key": "/sport/hockey/team:13", "value": 15}, "toronto_maple_leafs": {"team_key": "/sport/hockey/team:8", "value": 14}, "new_york_rangers": {"team_key": "/sport/hockey/team:6", "value": 10}, "philadelphia_flyers": {"team_key": "/sport/hockey/team:12", "value": 17}, "washington_capitals": {"team_key": "/sport/hockey/team:15", "value": 61}}}, "Bakersfield CA": {"min_value": 9, "values": {"los_angeles_kings": {"team_key": "/sport/hockey/team:23", "value": 36}, "san_jose_sharks": {"team_key": "/sport/hockey/team:21", "value": 9}, "toronto_maple_leafs": {"team_key": "/sport/hockey/team:8", "value": 12}, "edmonton_oilers": {"team_key": "/sport/hockey/team:24", "value": 28}, "anaheim_ducks": {"team_key": "/sport/hockey/team:25", "value": 18}}}, "Philadelphia PA": {"min_value": 17, "values": {"new_jersey_devils": {"team_key": "/sport/hockey/team:13", "value": 44}, "toronto_maple_leafs": {"team_key": "/sport/hockey/team:8", "value": 28}, "new_york_rangers": {"team_key": "/sport/hockey/team:6", "value": 17}, "philadelphia_flyers": {"team_key": "/sport/hockey/team:12", "value": 100}, "edmonton_oilers": {"team_key": "/sport/hockey/team:24", "value": 20}}}, "Idaho Falls-Pocatello ID": {"min_value": 6, "values": {"calgary_flames": {"team_key": "/sport/hockey/team:18", "value": 10}, "colorado_avalanche": {"team_key": "/sport/hockey/team:1", "value": 8}, "anaheim_ducks": {"team_key": "/sport/hockey/team:25", "value": 8}, "toronto_maple_leafs": {"team_key": "/sport/hockey/team:8", "value": 25}, "vancouver_canucks": {"team_key": "/sport/hockey/team:26", "value": 6}}}, "Shreveport LA": {"min_value": 3, "values": {"los_angeles_kings": {"team_key": "/sport/hockey/team:23", "value": 3}, "vancouver_canucks": {"team_key": "/sport/hockey/team:26", "value": 3}, "dallas_stars": {"team_key": "/sport/hockey/team:20", "value": 15}, "toronto_maple_leafs": {"team_key": "/sport/hockey/team:8", "value": 14}, "anaheim_ducks": {"team_key": "/sport/hockey/team:25", "value": 3}}}, "Beaumont-Port Arthur TX": {"min_value": 2, "values": {"los_angeles_kings": {"team_key": "/sport/hockey/team:23", "value": 2}, "dallas_stars": {"team_key": "/sport/hockey/team:20", "value": 10}, "new_york_rangers": {"team_key": "/sport/hockey/team:6", "value": 3}, "edmonton_oilers": {"team_key": "/sport/hockey/team:24", "value": 15}, "montreal_canadiens": {"team_key": "/sport/hockey/team:11", "value": 3}}}, "Baltimore MD": {"min_value": 9, "values": {"new_jersey_devils": {"team_key": "/sport/hockey/team:13", "value": 11}, "new_york_islanders": {"team_key": "/sport/hockey/team:4", "value": 9}, "toronto_maple_leafs": {"team_key": "/sport/hockey/team:8", "value": 17}, "washington_capitals": {"team_key": "/sport/hockey/team:15", "value": 73}, "edmonton_oilers": {"team_key": "/sport/hockey/team:24", "value": 10}}}, "Memphis TN": {"min_value": 5, "values": {"calgary_flames": {"team_key": "/sport/hockey/team:18", "value": 5}, "vancouver_canucks": {"team_key": "/sport/hockey/team:26", "value": 5}, "toronto_maple_leafs": {"team_key": "/sport/hockey/team:8", "value": 11}, "edmonton_oilers": {"team_key": "/sport/hockey/team:24", "value": 10}, "nashville_predators": {"team_key": "/sport/hockey/team:27", "value": 9}}}, "Helena Mount": {"min_value": 4, "values": {"chicago_blackhawks": {"team_key": "/sport/hockey/team:22", "value": 4}, "colorado_avalanche": {"team_key": "/sport/hockey/team:1", "value": 15}, "boston_bruins": {"team_key": "/sport/hockey/team:3", "value": 4}, "montreal_canadiens": {"team_key": "/sport/hockey/team:11", "value": 11}, "los_angeles_kings": {"team_key": "/sport/hockey/team:23", "value": 5}}}, "Sherman TX-Ada OK": {"min_value": 2, "values": {"nashville_predators": {"team_key": "/sport/hockey/team:27", "value": 2}, "san_jose_sharks": {"team_key": "/sport/hockey/team:21", "value": 3}, "new_york_rangers": {"team_key": "/sport/hockey/team:6", "value": 3}, "los_angeles_kings": {"team_key": "/sport/hockey/team:23", "value": 2}, "dallas_stars": {"team_key": "/sport/hockey/team:20", "value": 52}}}, "Salt Lake City UT": {"min_value": 7, "values": {"colorado_avalanche": {"team_key": "/sport/hockey/team:1", "value": 7}, "anaheim_ducks": {"team_key": "/sport/hockey/team:25", "value": 8}, "toronto_maple_leafs": {"team_key": "/sport/hockey/team:8", "value": 17}, "edmonton_oilers": {"team_key": "/sport/hockey/team:24", "value": 12}, "vancouver_canucks": {"team_key": "/sport/hockey/team:26", "value": 7}}}, "Burlington VT-Plattsburgh NY": {"min_value": 22, "values": {"boston_bruins": {"team_key": "/sport/hockey/team:3", "value": 36}, "new_york_rangers": {"team_key": "/sport/hockey/team:6", "value": 25}, "toronto_maple_leafs": {"team_key": "/sport/hockey/team:8", "value": 51}, "edmonton_oilers": {"team_key": "/sport/hockey/team:24", "value": 22}, "montreal_canadiens": {"team_key": "/sport/hockey/team:11", "value": 100}}}, "Odessa-Midland TX": {"min_value": 2, "values": {"vancouver_canucks": {"team_key": "/sport/hockey/team:26", "value": 2}, "san_jose_sharks": {"team_key": "/sport/hockey/team:21", "value": 2}, "dallas_stars": {"team_key": "/sport/hockey/team:20", "value": 27}, "toronto_maple_leafs": {"team_key": "/sport/hockey/team:8", "value": 10}, "new_york_rangers": {"team_key": "/sport/hockey/team:6", "value": 2}}}, "Topeka KS": {"min_value": 3, "values": {"calgary_flames": {"team_key": "/sport/hockey/team:18", "value": 6}, "st._louis_blues": {"team_key": "/sport/hockey/team:16", "value": 4}, "montreal_canadiens": {"team_key": "/sport/hockey/team:11", "value": 5}, "toronto_maple_leafs": {"team_key": "/sport/hockey/team:8", "value": 13}, "anaheim_ducks": {"team_key": "/sport/hockey/team:25", "value": 3}}}, "Harlingen-Weslaco-Brownsville-McAllen TX": {"min_value": 2, "values": {"vancouver_canucks": {"team_key": "/sport/hockey/team:26", "value": 2}, "dallas_stars": {"team_key": "/sport/hockey/team:20", "value": 4}, "toronto_maple_leafs": {"team_key": "/sport/hockey/team:8", "value": 15}, "edmonton_oilers": {"team_key": "/sport/hockey/team:24", "value": 6}, "winnipeg_jets": {"team_key": "/sport/hockey/team:28", "value": 8}}}, "St. Joseph MO": {"min_value": 0, "values": {"chicago_blackhawks": {"team_key": "/sport/hockey/team:22", "value": 2}, "st._louis_blues": {"team_key": "/sport/hockey/team:16", "value": 7}, "detroit_red_wings": {"team_key": "/sport/hockey/team:2", "value": 1}, "pittsburgh_penguins": {"team_key": "/sport/hockey/team:7", "value": 0}}}, "Raleigh-Durham (Fayetteville) NC": {"min_value": 7, "values": {"new_jersey_devils": {"team_key": "/sport/hockey/team:13", "value": 7}, "carolina_hurricanes": {"team_key": "/sport/hockey/team:5", "value": 100}, "toronto_maple_leafs": {"team_key": "/sport/hockey/team:8", "value": 20}, "edmonton_oilers": {"team_key": "/sport/hockey/team:24", "value": 11}, "winnipeg_jets": {"team_key": "/sport/hockey/team:28", "value": 7}}}, "Lima OH": {"min_value": 2, "values": {"boston_bruins": {"team_key": "/sport/hockey/team:3", "value": 2}, "san_jose_sharks": {"team_key": "/sport/hockey/team:21", "value": 6}, "columbus_blue_jackets": {"team_key": "/sport/hockey/team:30", "value": 29}, "detroit_red_wings": {"team_key": "/sport/hockey/team:2", "value": 6}, "anaheim_ducks": {"team_key": "/sport/hockey/team:25", "value": 5}}}, "Ft. Smith-Fayetteville-Springdale-Rogers AR": {"min_value": 4, "values": {"vancouver_canucks": {"team_key": "/sport/hockey/team:26", "value": 4}, "dallas_stars": {"team_key": "/sport/hockey/team:20", "value": 11}, "toronto_maple_leafs": {"team_key": "/sport/hockey/team:8", "value": 16}, "edmonton_oilers": {"team_key": "/sport/hockey/team:24", "value": 7}, "anaheim_ducks": {"team_key": "/sport/hockey/team:25", "value": 6}}}, "Atlanta GA": {"min_value": 5, "values": {"new_jersey_devils": {"team_key": "/sport/hockey/team:13", "value": 5}, "montreal_canadiens": {"team_key": "/sport/hockey/team:11", "value": 5}, "toronto_maple_leafs": {"team_key": "/sport/hockey/team:8", "value": 15}, "edmonton_oilers": {"team_key": "/sport/hockey/team:24", "value": 7}, "winnipeg_jets": {"team_key": "/sport/hockey/team:28", "value": 7}}}, "Louisville KY": {"min_value": 4, "values": {"new_jersey_devils": {"team_key": "/sport/hockey/team:13", "value": 4}, "nashville_predators": {"team_key": "/sport/hockey/team:27", "value": 9}, "toronto_maple_leafs": {"team_key": "/sport/hockey/team:8", "value": 16}, "edmonton_oilers": {"team_key": "/sport/hockey/team:24", "value": 11}, "winnipeg_jets": {"team_key": "/sport/hockey/team:28", "value": 5}}}, "Youngstown OH": {"min_value": 7, "values": {"new_jersey_devils": {"team_key": "/sport/hockey/team:13", "value": 7}, "columbus_blue_jackets": {"team_key": "/sport/hockey/team:30", "value": 8}, "toronto_maple_leafs": {"team_key": "/sport/hockey/team:8", "value": 28}, "pittsburgh_penguins": {"team_key": "/sport/hockey/team:7", "value": 20}, "calgary_flames": {"team_key": "/sport/hockey/team:18", "value": 7}}}, "Erie PA": {"min_value": 10, "values": {"new_jersey_devils": {"team_key": "/sport/hockey/team:13", "value": 11}, "toronto_maple_leafs": {"team_key": "/sport/hockey/team:8", "value": 51}, "pittsburgh_penguins": {"team_key": "/sport/hockey/team:7", "value": 35}, "edmonton_oilers": {"team_key": "/sport/hockey/team:24", "value": 30}, "winnipeg_jets": {"team_key": "/sport/hockey/team:28", "value": 10}}}, "Harrisonburg VA": {"min_value": 8, "values": {"new_jersey_devils": {"team_key": "/sport/hockey/team:13", "value": 10}, "calgary_flames": {"team_key": "/sport/hockey/team:18", "value": 8}, "new_york_rangers": {"team_key": "/sport/hockey/team:6", "value": 9}, "toronto_maple_leafs": {"team_key": "/sport/hockey/team:8", "value": 24}, "washington_capitals": {"team_key": "/sport/hockey/team:15", "value": 45}}}, "Jonesboro AR": {"min_value": 1, "values": {"boston_bruins": {"team_key": "/sport/hockey/team:3", "value": 1}, "st._louis_blues": {"team_key": "/sport/hockey/team:16", "value": 3}, "nashville_predators": {"team_key": "/sport/hockey/team:27", "value": 3}, "pittsburgh_penguins": {"team_key": "/sport/hockey/team:7", "value": 1}, "chicago_blackhawks": {"team_key": "/sport/hockey/team:22", "value": 2}}}, "Champaign & Springfield-Decatur IL": {"min_value": 10, "values": {"chicago_blackhawks": {"team_key": "/sport/hockey/team:22", "value": 27}, "st._louis_blues": {"team_key": "/sport/hockey/team:16", "value": 15}, "toronto_maple_leafs": {"team_key": "/sport/hockey/team:8", "value": 22}, "edmonton_oilers": {"team_key": "/sport/hockey/team:24", "value": 12}, "winnipeg_jets": {"team_key": "/sport/hockey/team:28", "value": 10}}}, "Sioux Falls(Mitchell) SD": {"min_value": 10, "values": {"calgary_flames": {"team_key": "/sport/hockey/team:18", "value": 10}, "toronto_maple_leafs": {"team_key": "/sport/hockey/team:8", "value": 17}, "minnesota_wild": {"team_key": "/sport/hockey/team:29", "value": 17}, "edmonton_oilers": {"team_key": "/sport/hockey/team:24", "value": 19}, "winnipeg_jets": {"team_key": "/sport/hockey/team:28", "value": 12}}}, "Columbus-Tupelo-West Point MS": {"min_value": 4, "values": {"toronto_maple_leafs": {"team_key": "/sport/hockey/team:8", "value": 11}, "calgary_flames": {"team_key": "/sport/hockey/team:18", "value": 7}, "new_york_islanders": {"team_key": "/sport/hockey/team:4", "value": 4}, "montreal_canadiens": {"team_key": "/sport/hockey/team:11", "value": 4}, "nashville_predators": {"team_key": "/sport/hockey/team:27", "value": 4}}}, "Ottumwa IA-Kirksville MO": {"min_value": 5, "values": {"chicago_blackhawks": {"team_key": "/sport/hockey/team:22", "value": 8}, "st._louis_blues": {"team_key": "/sport/hockey/team:16", "value": 12}, "dallas_stars": {"team_key": "/sport/hockey/team:20", "value": 6}, "calgary_flames": {"team_key": "/sport/hockey/team:18", "value": 11}, "montreal_canadiens": {"team_key": "/sport/hockey/team:11", "value": 5}}}, "Tucson (Sierra Vista) AZ": {"min_value": 8, "values": {"calgary_flames": {"team_key": "/sport/hockey/team:18", "value": 9}, "vancouver_canucks": {"team_key": "/sport/hockey/team:26", "value": 8}, "arizona_coyotes": {"team_key": "/sport/hockey/team:19", "value": 23}, "toronto_maple_leafs": {"team_key": "/sport/hockey/team:8", "value": 15}, "edmonton_oilers": {"team_key": "/sport/hockey/team:24", "value": 11}}}, "Greenville-New Bern-Washington NC": {"min_value": 6, "values": {"new_jersey_devils": {"team_key": "/sport/hockey/team:13", "value": 6}, "carolina_hurricanes": {"team_key": "/sport/hockey/team:5", "value": 29}, "montreal_canadiens": {"team_key": "/sport/hockey/team:11", "value": 7}, "toronto_maple_leafs": {"team_key": "/sport/hockey/team:8", "value": 13}, "edmonton_oilers": {"team_key": "/sport/hockey/team:24", "value": 9}}}, "Richmond-Petersburg VA": {"min_value": 8, "values": {"new_jersey_devils": {"team_key": "/sport/hockey/team:13", "value": 9}, "new_york_islanders": {"team_key": "/sport/hockey/team:4", "value": 8}, "toronto_maple_leafs": {"team_key": "/sport/hockey/team:8", "value": 19}, "washington_capitals": {"team_key": "/sport/hockey/team:15", "value": 34}, "edmonton_oilers": {"team_key": "/sport/hockey/team:24", "value": 9}}}, "Fairbanks AK": {"min_value": 7, "values": {"los_angeles_kings": {"team_key": "/sport/hockey/team:23", "value": 9}, "colorado_avalanche": {"team_key": "/sport/hockey/team:1", "value": 7}, "anaheim_ducks": {"team_key": "/sport/hockey/team:25", "value": 13}, "toronto_maple_leafs": {"team_key": "/sport/hockey/team:8", "value": 17}, "vancouver_canucks": {"team_key": "/sport/hockey/team:26", "value": 8}}}, "Baton Rouge LA": {"min_value": 3, "values": {"calgary_flames": {"team_key": "/sport/hockey/team:18", "value": 5}, "new_york_islanders": {"team_key": "/sport/hockey/team:4", "value": 3}, "dallas_stars": {"team_key": "/sport/hockey/team:20", "value": 3}, "toronto_maple_leafs": {"team_key": "/sport/hockey/team:8", "value": 9}, "anaheim_ducks": {"team_key": "/sport/hockey/team:25", "value": 3}}}, "Abilene-Sweetwater TX": {"min_value": 11, "values": {"new_jersey_devils": {"team_key": "/sport/hockey/team:13", "value": 12}, "vancouver_canucks": {"team_key": "/sport/hockey/team:26", "value": 11}, "dallas_stars": {"team_key": "/sport/hockey/team:20", "value": 19}, "toronto_maple_leafs": {"team_key": "/sport/hockey/team:8", "value": 17}, "edmonton_oilers": {"team_key": "/sport/hockey/team:24", "value": 22}}}, "Reno NV": {"min_value": 9, "values": {"los_angeles_kings": {"team_key": "/sport/hockey/team:23", "value": 14}, "vancouver_canucks": {"team_key": "/sport/hockey/team:26", "value": 9}, "san_jose_sharks": {"team_key": "/sport/hockey/team:21", "value": 33}, "toronto_maple_leafs": {"team_key": "/sport/hockey/team:8", "value": 19}, "anaheim_ducks": {"team_key": "/sport/hockey/team:25", "value": 16}}}, "Sacramento-Stockton-Modesto CA": {"min_value": 8, "values": {"los_angeles_kings": {"team_key": "/sport/hockey/team:23", "value": 9}, "san_jose_sharks": {"team_key": "/sport/hockey/team:21", "value": 40}, "toronto_maple_leafs": {"team_key": "/sport/hockey/team:8", "value": 14}, "edmonton_oilers": {"team_key": "/sport/hockey/team:24", "value": 10}, "anaheim_ducks": {"team_key": "/sport/hockey/team:25", "value": 8}}}, "San Angelo TX": {"min_value": 1, "values": {"boston_bruins": {"team_key": "/sport/hockey/team:3", "value": 1}, "san_jose_sharks": {"team_key": "/sport/hockey/team:21", "value": 3}, "new_york_rangers": {"team_key": "/sport/hockey/team:6", "value": 2}, "los_angeles_kings": {"team_key": "/sport/hockey/team:23", "value": 7}, "dallas_stars": {"team_key": "/sport/hockey/team:20", "value": 25}}}, "Chico-Redding CA": {"min_value": 8, "values": {"calgary_flames": {"team_key": "/sport/hockey/team:18", "value": 8}, "vancouver_canucks": {"team_key": "/sport/hockey/team:26", "value": 9}, "san_jose_sharks": {"team_key": "/sport/hockey/team:21", "value": 42}, "toronto_maple_leafs": {"team_key": "/sport/hockey/team:8", "value": 14}, "anaheim_ducks": {"team_key": "/sport/hockey/team:25", "value": 10}}}, "Huntsville-Decatur (Florence) AL": {"min_value": 4, "values": {"calgary_flames": {"team_key": "/sport/hockey/team:18", "value": 4}, "nashville_predators": {"team_key": "/sport/hockey/team:27", "value": 12}, "toronto_maple_leafs": {"team_key": "/sport/hockey/team:8", "value": 17}, "edmonton_oilers": {"team_key": "/sport/hockey/team:24", "value": 9}, "anaheim_ducks": {"team_key": "/sport/hockey/team:25", "value": 4}}}}